Workbook

Sheet README
A1: NETGEAR BoM Catalog — Read Me
A2: Built from 5 datasheets (M4250, M4350, PR460X, WBE718, WBE758). Font: Outfit (install from fonts.google.com/specimen/Outfit if it doesn't render).
A4: Purpose | B4: Single source of product data for the Network BOM Builder: the tool reads these tables to pick switches, PSUs, optics and support SKUs from IDF/MDF, endpoint and redundancy inputs.
A6: Sheet | B6: What it holds
A7: Products | B7: One row per base model. Physical, ports, PoE, power, performance, AV features, environment, commercial. Key = Product_ID.
A8: SKUs | B8: Every orderable variant (region, TAA). Many-to-one with Products.
A9: Accessories | B9: PSUs, adapters, optics, DACs/AOCs, trays, licenses, support packs. Key = Orderable_SKU, grouped by Base_Model.
A10: Compatibility | B10: Which accessories fit which product or family, with slot/port type and max qty.
A11: PSU_PoE_Matrix | B11: Exact PoE budget for every PSU combination (EPS total + protected/RPS). Use this rather than a single 'max' number.
A12: Design_Rules | B12: Footnote-level constraints the engine must enforce (25G block speed, stacking vs AVB/PTP, PoE classes, Insight vs Engage...).
A13: Model_Lookup | B13: Example of formula-driven lookups against the tables.
A14: Data_Dictionary | B14: Every column with unit/type, plus recommended future fields.
A15: Data_Gaps | B15: Datasheet conflicts and missing data, with the assumption loaded.
A16: Endpoints | B16: Endpoint library the BoM tool loads: link speed, media, PoE allocation, stream Mbps.
... A19: Lists | B19: Dropdown values used for data validation.
A21: How to add a new switch
A22: 1 | B22: Products: type in the first empty row directly under the table - it auto-expands. Fill at minimum Product_ID, Model_Name, Family, Category, Status, port counts, PoE and PSU fields, Source_Datasheet.
A23: 2 | B23: Grey columns are formulas; if Excel doesn't auto-fill them, copy the formula from the row above.
A24: 3 | B24: SKUs: add one row per regional/TAA orderable SKU.
A25: 4 | B25: Accessories: add any new PSU/optic/support SKU. Compatibility: add Product- or Family-scoped rows (a Family row covers all its models).
A26: 4b | B26: New port speed (e.g. 50G): add a Ports_ column in Products next to the others and a matching row in Port_Types.
A27: 5 | B27: If the switch has modular PSUs, add its combinations to PSU_PoE_Matrix. Add any footnote constraint to Design_Rules.
A28: 6 | B28: Log conflicts in Data_Gaps and set Last_Verified.
A30: Conventions | B30: Units are in the column header (W, mm, kg, Gbps). Numbers stored as numbers; blank = not applicable / not stated. Never overwrite a datasheet value with an estimate - use Data_Notes.
A31: Legend | B31: Grey fill = calculated · Yellow fill = to be filled from price book / PLM · Blue text = user input in Model_Lookup
A32: Sources | B32: M4250: DS-M4250-9Nov23 · M4350: DS-M4350-30May25 (uploaded as 'M3450_Datasheet_30May25.pdf') · PR460X: NG_DS_AV_PR460X-042926 · WBE718: DS-WBE718_02Apr26 · WBE758: D-WBE758_29Jan24 · 25G/100G optics & DACs: optic.ca, NETGEAR KB 000066694 (updated 2025-09-23)
A34: Catalog counts
A35: Products | B35: =COUNTA(Products!A5:A1000)
A36: Orderable SKUs | B36: =COUNTA(SKUs!C5:C2000)
A37: Accessory SKUs | B37: =COUNTA(Accessories!A5:A2000)
A38: PSU configs | B38: =COUNTA(PSU_PoE_Matrix!A5:A2000)
A39: Open gaps | B39: =COUNTA(Data_Gaps!A5:A500)

Sheet Products
A1: NETGEAR BoM Catalog — Products (one row per base model)
A2: Grey = calculated (copy formula down for new rows) · Yellow = to fill from price book/PLM · Green band = attribute group · Key column: Product_ID
A3: Identity | H3: Commercial | L3: Physical | S3: Ports | AI3: PoE (PSE) | AP3: PoE (PD) | AS3: Power | BB3: Performance | BK3: Features | BT3: Environment | BY3: Commercial | CC3: Router | CG3: Wireless | CK3: Governance
A4: Product_ID | B4: Model_Name | C4: Family | D4: Product_Line | E4: Category | F4: Role | G4: Management | H4: Lifecycle_Status | I4: List_Price_USD | J4: Lead_Time_Wks | K4: EOS_Date | L4: Form_Factor | M4: Rack_Units | N4: Width_Class | O4: Width_mm | P4: Depth_mm | Q4: Height_mm | R4: Weight_kg | S4: Ports_1G_RJ45 | T4: Ports_2.5G_RJ45 | U4: Ports_10G_RJ45 | V4: Ports_SFP_1G | W4: Ports_SFP_2.5G | X4: Ports_SFP+_10G | Y4: Ports_SFP28_25G | Z4: Ports_QSFP28_100G | AA4: Ports_5G_RJ45 | AB4: Ports_SFP56_50G | AC4: Ports_QSFP56_200G | AD4: Ports_QSFPDD_400G | AE4: Ports_Combo_10G | AF4: Total_Ports | AG4: Max_1G_SFP_Modules | AH4: Port_Speed_Constraints | AI4: PoE_Ports | AJ4: PoE_Standard | AK4: PoE_Max_W_per_Port | AL4: PoE_Budget_Base_W | AM4: PoE_Budget_Max_W | AN4: PoE_Budget_Redundant_Max_W | AO4: PoE_Avg_W_per_Port_at_Max | AP4: PD_Max_Draw_W | AQ4: PD_Required_PoE | AR4: PD_Uplink_Speed | AS4: PSU_Type | AT4: PSU_Internal_W | AU4: PSU_Fixed_Qty | AV4: PSU_Modular_Slots | AW4: PSU_Compat_Group | AX4: Power_Idle_W | AY4: Power_Max_NoPoE_W | AZ4: Power_Max_FullPoE_W | BA4: Heat_Max_BTU_hr | BB4: Switching_Fabric_Gbps | BC4: Throughput_Mpps | BD4: Packet_Buffer_Mb | BE4: RAM_GB | BF4: CPU | BG4: MAC_Table | BH4: Max_VLANs | BI4: IGMP_Groups | BJ4: Max_LAGs | BK4: L3_Feature_Set | BL4: Stacking | BM4: Stack_Max_Units | BN4: AVB | BO4: PTP | BP4: SMPTE_ST2110 | BQ4: IGMP_Plus | BR4: Engage_Support | BS4: Insight_Support | BT4: OpTemp_Max_C | BU4: Airflow | BV4: Fan_Off_Mode | BW4: Acoustic_Quiet_25C_dBA | BX4: MTBF_25C_hours | BY4: Warranty | BZ4: Support_Category | CA4: TAA_SKU | CB4: Included_Subscription | CC4: WAN_Ports | CD4: WAN_Throughput | CE4: VPN_Capacity | CF4: Max_Clients | CG4: WiFi_Standard | CH4: WiFi_Streams | CI4: WiFi_Max_Gbps | CJ4: SSIDs | CK4: Source_Datasheet | CL4: Last_Verified | CM4: Data_Notes
A5: GSM4210PD | B5: M4250-9G1F-PoE+ | C5: M4250 | D5: NETGEAR AV Line | E5: Switch | F5: Access / Edge | G5: AV UI; Engage; IT Web GUI; CLI; SNMP | H5: Active | L5: Desktop | N5: Desktop | O5: 210 | P5: 140 | Q5: 40 | R5: 0.965 | S5: 9 | T5: 0 | U5: 0 | V5: 1 | W5: 0 | X5: 0 | Y5: 0 | Z5: 0 | AA5: 0 | AB5: 0 | AC5: 0 | AD5: 0 | AE5: 0 | AF5: =SUM(S5:AE5) | AI5: 8 | AJ5: 802.3at PoE+ | AK5: 30 | AL5: 110 | AM5: 110 | AO5: =IFERROR(AM5/AI5,"") | AS5: External adapter (130W, included) | AU5: 1 | AV5: 0 | AW5: None (fixed) | AX5: 6.4 | AY5: 9.88 | AZ5: 132.25 | BA5: =IF(MAX(AY5,AZ5)=0,"",ROUND(MAX(AY5,AZ5)*3.412,0)) | BB5: 20 | BC5: 14.88 | BD5: 16 | BE5: 2 | BF5: ARM A9 1.25GHz | BG5: 16384 | BH5: 4093 | BI5: 2K IPv4 / 2K IPv6 | BJ5: 8 x 8 ports | BK5: Lite L3 (static, RIP, PIM-SM/DM, DHCP server) | BL5: No | BN5: Yes (256 streams; not on LAG) | BO5: PTPv2 1-step E2E Transparent Clock | BP5: No | BQ5: Yes | BR5: Yes | BS5: No | BT5: 45 | BU5: Fanless | BV5: Fanless | BW5: 0 | BX5: 1020808 | BY5: ProSAFE Limited Lifetime HW; Lifetime NBD replacement | BZ5: Cat 2 | CA5: Not listed | CK5: M4250 datasheet DS-M4250-9Nov23 (fw 13.0.4) | CL5: 2026-09-27 | CM5: Throughput 14.88 Mpps (perf table) vs 14.80 Mpps (spec table) - verify
A6: GSM4210PX | B6: M4250-8G2XF-PoE+ | C6: M4250 | D6: NETGEAR AV Line | E6: Switch | F6: Access / Edge | G6: AV UI; Engage; IT Web GUI; CLI; SNMP | H6: Active | L6: Desktop | N6: Desktop | O6: 210 | P6: 140 | Q6: 40 | R6: 0.967 | S6: 8 | T6: 0 | U6: 0 | V6: 0 | W6: 0 | X6: 2 | Y6: 0 | Z6: 0 | AA6: 0 | AB6: 0 | AC6: 0 | AD6: 0 | AE6: 0 | AF6: =SUM(S6:AE6) | AI6: 8 | AJ6: 802.3at PoE+ | AK6: 30 | AL6: 220 | AM6: 220 | AO6: =IFERROR(AM6/AI6,"") | AS6: External adapter APS254W (included) | AU6: 1 | AV6: 0 | AW6: None (fixed) | AX6: 9.51 | AY6: 18.14 | AZ6: 257.9 | BA6: =IF(MAX(AY6,AZ6)=0,"",ROUND(MAX(AY6,AZ6)*3.412,0)) | BB6: 56 | BC6: 41.67 | BD6: 16 | BE6: 2 | BF6: ARM A9 1.25GHz | BG6: 16384 | BH6: 4093 | BI6: 2K IPv4 / 2K IPv6 | BJ6: 8 x 8 ports | BK6: Lite L3 (static, RIP, PIM-SM/DM, DHCP server) | BL6: No | BN6: Yes (256 streams; not on LAG) | BO6: PTPv2 1-step E2E Transparent Clock | BP6: No | BQ6: Yes | BR6: Yes | BS6: No | BT6: 45 | BU6: Side-to-side | BV6: Yes (up to 180W PoE, RJ45 only) | BW6: 19.3 | BX6: 1484652 | BY6: ProSAFE Limited Lifetime HW; Lifetime NBD replacement | BZ6: Cat 2 | CA6: Not listed | CK6: M4250 datasheet DS-M4250-9Nov23 (fw 13.0.4) | CL6: 2026-09-27
A7: GSM4212P | B7: M4250-10G2F-PoE+ | C7: M4250 | D7: NETGEAR AV Line | E7: Switch | F7: Access / Edge | G7: AV UI; Engage; IT Web GUI; CLI; SNMP | H7: Active | L7: 1U rack | M7: 1 | N7: Full width | O7: 440 | P7: 200 | Q7: 43.2 | R7: 2.85 | S7: 10 | T7: 0 | U7: 0 | V7: 2 | W7: 0 | X7: 0 | Y7: 0 | Z7: 0 | AA7: 0 | AB7: 0 | AC7: 0 | AD7: 0 | AE7: 0 | AF7: =SUM(S7:AE7) | AI7: 8 | AJ7: 802.3at PoE+ | AK7: 30 | AL7: 125 | AM7: 125 | AO7: =IFERROR(AM7/AI7,"") | AS7: Internal fixed (C14) | AU7: 1 | AV7: 0 | AW7: None (fixed) | AX7: 8.53 | AY7: 17.32 | AZ7: 163.9 | BA7: =IF(MAX(AY7,AZ7)=0,"",ROUND(MAX(AY7,AZ7)*3.412,0)) | BB7: 24 | BC7: 17.86 | BD7: 16 | BE7: 2 | BF7: ARM A9 1.25GHz | BG7: 16384 | BH7: 4093 | BI7: 2K IPv4 / 2K IPv6 | BJ7: 8 x 8 ports | BK7: Lite L3 (static, RIP, PIM-SM/DM, DHCP server) | BL7: No | BN7: Yes (256 streams; not on LAG) | BO7: PTPv2 1-step E2E Transparent Clock | BP7: No | BQ7: Yes | BR7: Yes | BS7: No | BT7: 45 | BU7: Side-to-side | BV7: Yes (up to 80W PoE) | BW7: 27.38 | BX7: 778769 | BY7: ProSAFE Limited Lifetime HW; Lifetime NBD replacement | BZ7: Cat 2 | CA7: Not listed | CK7: M4250 datasheet DS-M4250-9Nov23 (fw 13.0.4) | CL7: 2026-09-27
A8: GSM4212PX | B8: M4250-10G2XF-PoE+ | C8: M4250 | D8: NETGEAR AV Line | E8: Switch | F8: Access / Edge | G8: AV UI; Engage; IT Web GUI; CLI; SNMP | H8: Active | L8: 1U rack | M8: 1 | N8: Full width | O8: 440 | P8: 200 | Q8: 43.2 | R8: 2.9 | S8: 10 | T8: 0 | U8: 0 | V8: 0 | W8: 0 | X8: 2 | Y8: 0 | Z8: 0 | AA8: 0 | AB8: 0 | AC8: 0 | AD8: 0 | AE8: 0 | AF8: =SUM(S8:AE8) | AI8: 8 | AJ8: 802.3at PoE+ | AK8: 30 | AL8: 240 | AM8: 240 | AO8: =IFERROR(AM8/AI8,"") | AS8: Internal fixed (C14) | AU8: 1 | AV8: 0 | AW8: None (fixed) | AX8: 12.96 | AY8: 25 | AZ8: 306.4 | BA8: =IF(MAX(AY8,AZ8)=0,"",ROUND(MAX(AY8,AZ8)*3.412,0)) | BB8: 60 | BC8: 44.64 | BD8: 16 | BE8: 2 | BF8: ARM A9 1.25GHz | BG8: 16384 | BH8: 4093 | BI8: 2K IPv4 / 2K IPv6 | BJ8: 8 x 8 ports | BK8: Lite L3 (static, RIP, PIM-SM/DM, DHCP server) | BL8: No | BN8: Yes (256 streams; not on LAG) | BO8: PTPv2 1-step E2E Transparent Clock | BP8: No | BQ8: Yes | BR8: Yes | BS8: No | BT8: 45 | BU8: Side-to-side | BV8: Yes (up to 90W PoE) | BW8: 27.4 | BX8: 576889 | BY8: ProSAFE Limited Lifetime HW; Lifetime NBD replacement | BZ8: Cat 2 | CA8: Not listed | CK8: M4250 datasheet DS-M4250-9Nov23 (fw 13.0.4) | CL8: 2026-09-27
A9: GSM4212UX | B9: M4250-10G2XF-PoE++ | C9: M4250 | D9: NETGEAR AV Line | E9: Switch | F9: Access / Edge | G9: AV UI; Engage; IT Web GUI; CLI; SNMP | H9: Active | L9: 1U rack | M9: 1 | N9: Full width | O9: 440 | P9: 257 | Q9: 43.2 | R9: 3.83 | S9: 10 | T9: 0 | U9: 0 | V9: 0 | W9: 0 | X9: 2 | Y9: 0 | Z9: 0 | AA9: 0 | AB9: 0 | AC9: 0 | AD9: 0 | AE9: 0 | AF9: =SUM(S9:AE9) | AI9: 8 | AJ9: 802.3bt Ultra90 PoE++ | AK9: 90 | AL9: 720 | AM9: 720 | AO9: =IFERROR(AM9/AI9,"") | AS9: Internal fixed (C14) | AU9: 1 | AV9: 0 | AW9: None (fixed) | AX9: 18 | AY9: 26.3 | AZ9: 837.7 | BA9: =IF(MAX(AY9,AZ9)=0,"",ROUND(MAX(AY9,AZ9)*3.412,0)) | BB9: 60 | BC9: 44.64 | BD9: 16 | BE9: 2 | BF9: ARM A9 1.25GHz | BG9: 16384 | BH9: 4093 | BI9: 2K IPv4 / 2K IPv6 | BJ9: 8 x 8 ports | BK9: Lite L3 (static, RIP, PIM-SM/DM, DHCP server) | BL9: No | BN9: Yes (256 streams; not on LAG) | BO9: PTPv2 1-step E2E Transparent Clock | BP9: No | BQ9: Yes | BR9: Yes | BS9: No | BT9: 45 | BU9: Side-to-side | BV9: Yes (up to 45W PoE) | BW9: 34.57 | BX9: 947871 | BY9: ProSAFE Limited Lifetime HW; Lifetime NBD replacement | BZ9: Cat 2 | CA9: Not listed | CK9: M4250 datasheet DS-M4250-9Nov23 (fw 13.0.4) | CL9: 2026-09-27
A10: GSM4230P | B10: M4250-26G4F-PoE+ | C10: M4250 | D10: NETGEAR AV Line | E10: Switch | F10: Access / Edge | G10: AV UI; Engage; IT Web GUI; CLI; SNMP | H10: Active | L10: 1U rack | M10: 1 | N10: Full width | O10: 440 | P10: 257 | Q10: 43.2 | R10: 4.3 | S10: 26 | T10: 0 | U10: 0 | V10: 4 | W10: 0 | X10: 0 | Y10: 0 | Z10: 0 | AA10: 0 | AB10: 0 | AC10: 0 | AD10: 0 | AE10: 0 | AF10: =SUM(S10:AE10) | AI10: 24 | AJ10: 802.3at PoE+ | AK10: 30 | AL10: 300 | AM10: 300 | AO10: =IFERROR(AM10/AI10,"") | AS10: Internal fixed (C14) | AU10: 1 | AV10: 0 | AW10: None (fixed) | AX10: 23.4 | AY10: 35.8 | AZ10: 401 | BA10: =IF(MAX(AY10,AZ10)=0,"",ROUND(MAX(AY10,AZ10)*3.412,0)) | BB10: 60 | BC10: 44.64 | BD10: 16 | BE10: 2 | BF10: Quad-core Cortex-A57 1.8GHz | BG10: 16384 | BH10: 4093 | BI10: 2K IPv4 / 2K IPv6 | BJ10: 8 x 8 ports | BK10: Lite L3 (static, RIP, PIM-SM/DM, DHCP server) | BL10: No | BN10: Yes (256 streams; not on LAG) | BO10: PTPv2 1-step E2E Transparent Clock | BP10: No | BQ10: Yes | BR10: Yes | BS10: No | BT10: 45 | BU10: Side-to-side | BV10: Yes (up to 45W PoE, 8 ports) | BW10: 28 | BX10: 511054 | BY10: ProSAFE Limited Lifetime HW; Lifetime NBD replacement | BZ10: Cat 2 | CA10: Not listed | CK10: M4250 datasheet DS-M4250-9Nov23 (fw 13.0.4) | CL10: 2026-09-27
A11: GSM4230UP | B11: M4250-26G4F-PoE++ | C11: M4250 | D11: NETGEAR AV Line | E11: Switch | F11: Access / Edge | G11: AV UI; Engage; IT Web GUI; CLI; SNMP | H11: Active | L11: 1U rack | M11: 1 | N11: Full width | O11: 440 | P11: 400 | Q11: 43.2 | R11: 6.746 | S11: 26 | T11: 0 | U11: 0 | V11: 4 | W11: 0 | X11: 0 | Y11: 0 | Z11: 0 | AA11: 0 | AB11: 0 | AC11: 0 | AD11: 0 | AE11: 0 | AF11: =SUM(S11:AE11) | AI11: 24 | AJ11: 802.3bt Ultra90 PoE++ | AK11: 90 | AL11: 720 | AM11: 1440 | AO11: =IFERROR(AM11/AI11,"") | AS11: 2x internal fixed (C14), RPS/EPS | AU11: 2 | AV11: 0 | AW11: None (fixed) | AX11: 36.9 | AY11: 48.8 | AZ11: 1734 | BA11: =IF(MAX(AY11,AZ11)=0,"",ROUND(MAX(AY11,AZ11)*3.412,0)) | BB11: 60 | BC11: 44.64 | BD11: 16 | BE11: 2 | BF11: Quad-core Cortex-A57 1.8GHz | BG11: 16384 | BH11: 4093 | BI11: 2K IPv4 / 2K IPv6 | BJ11: 8 x 8 ports | BK11: Lite L3 (static, RIP, PIM-SM/DM, DHCP server) | BL11: No | BN11: Yes (256 streams; not on LAG) | BO11: PTPv2 1-step E2E Transparent Clock | BP11: No | BQ11: Yes | BR11: Yes | BS11: No | BT11: 45 | BU11: Side-to-side | BV11: No | BW11: 28 | BX11: 491282 | BY11: ProSAFE Limited Lifetime HW; Lifetime NBD replacement | BZ11: Cat 3 | CA11: Not listed | CK11: M4250 datasheet DS-M4250-9Nov23 (fw 13.0.4) | CL11: 2026-09-27 | CM11: PoE budget 720W with 1 PSU powered, 1,440W with 2. Full-PoE power: 889W (1 PSU) / 1,734W (2 PSU)
A12: GSM4230PX | B12: M4250-26G4XF-PoE+ | C12: M4250 | D12: NETGEAR AV Line | E12: Switch | F12: Access / Edge | G12: AV UI; Engage; IT Web GUI; CLI; SNMP | H12: Active | L12: 1U rack | M12: 1 | N12: Full width | O12: 440 | P12: 400 | Q12: 43.2 | R12: 5.453 | S12: 26 | T12: 0 | U12: 0 | V12: 0 | W12: 0 | X12: 4 | Y12: 0 | Z12: 0 | AA12: 0 | AB12: 0 | AC12: 0 | AD12: 0 | AE12: 0 | AF12: =SUM(S12:AE12) | AI12: 24 | AJ12: 802.3at PoE+ | AK12: 30 | AL12: 480 | AM12: 480 | AO12: =IFERROR(AM12/AI12,"") | AS12: Internal fixed (C14) | AU12: 1 | AV12: 0 | AW12: None (fixed) | AX12: 33.9 | AY12: 46.8 | AZ12: 614 | BA12: =IF(MAX(AY12,AZ12)=0,"",ROUND(MAX(AY12,AZ12)*3.412,0)) | BB12: 132 | BC12: 98.21 | BD12: 16 | BE12: 2 | BF12: Quad-core Cortex-A57 1.8GHz | BG12: 16384 | BH12: 4093 | BI12: 2K IPv4 / 2K IPv6 | BJ12: 8 x 8 ports | BK12: Lite L3 (static, RIP, PIM-SM/DM, DHCP server) | BL12: No | BN12: Yes (256 streams; not on LAG) | BO12: PTPv2 1-step E2E Transparent Clock | BP12: No | BQ12: Yes | BR12: Yes | BS12: No | BT12: 45 | BU12: Side-to-side | BV12: Yes (up to 45W PoE, 8 ports) | BW12: 25 | BX12: 509057 | BY12: ProSAFE Limited Lifetime HW; Lifetime NBD replacement | BZ12: Cat 3 | CA12: Not listed | CK12: M4250 datasheet DS-M4250-9Nov23 (fw 13.0.4) | CL12: 2026-09-27
A13: GSM4248P | B13: M4250-40G8F-PoE+ | C13: M4250 | D13: NETGEAR AV Line | E13: Switch | F13: Access / Edge | G13: AV UI; Engage; IT Web GUI; CLI; SNMP | H13: Active | L13: 1U rack | M13: 1 | N13: Full width | O13: 440 | P13: 400 | Q13: 43.2 | R13: 5.852 | S13: 40 | T13: 0 | U13: 0 | V13: 8 | W13: 0 | X13: 0 | Y13: 0 | Z13: 0 | AA13: 0 | AB13: 0 | AC13: 0 | AD13: 0 | AE13: 0 | AF13: =SUM(S13:AE13) | AI13: 40 | AJ13: 802.3at PoE+ | AK13: 30 | AL13: 480 | AM13: 480 | AO13: =IFERROR(AM13/AI13,"") | AS13: Internal fixed (C14) | AU13: 1 | AV13: 0 | AW13: None (fixed) | AX13: 46.4 | AY13: 59.5 | AZ13: 624.8 | BA13: =IF(MAX(AY13,AZ13)=0,"",ROUND(MAX(AY13,AZ13)*3.412,0)) | BB13: 96 | BC13: 71.42 | BD13: 32 | BE13: 2 | BF13: Quad-core Cortex-A57 1.8GHz | BG13: 16384 | BH13: 4093 | BI13: 2K IPv4 / 2K IPv6 | BJ13: 8 x 8 ports | BK13: Lite L3 (static, RIP, PIM-SM/DM, DHCP server) | BL13: No | BN13: Yes (256 streams; not on LAG) | BO13: PTPv2 1-step E2E Transparent Clock | BP13: No | BQ13: Yes | BR13: Yes | BS13: No | BT13: 45 | BU13: Side-to-side | BV13: Yes (up to 30W PoE, 8 ports) | BW13: 30 | BX13: 341680 | BY13: ProSAFE Limited Lifetime HW; Lifetime NBD replacement | BZ13: Cat 3 | CA13: Not listed | CK13: M4250 datasheet DS-M4250-9Nov23 (fw 13.0.4) | CL13: 2026-09-27
A14: GSM4248PX | B14: M4250-40G8XF-PoE+ | C14: M4250 | D14: NETGEAR AV Line | E14: Switch | F14: Access / Edge | G14: AV UI; Engage; IT Web GUI; CLI; SNMP | H14: Active | L14: 1U rack | M14: 1 | N14: Full width | O14: 440 | P14: 400 | Q14: 43.2 | R14: 6.312 | S14: 40 | T14: 0 | U14: 0 | V14: 0 | W14: 0 | X14: 8 | Y14: 0 | Z14: 0 | AA14: 0 | AB14: 0 | AC14: 0 | AD14: 0 | AE14: 0 | AF14: =SUM(S14:AE14) | AI14: 40 | AJ14: 802.3at PoE+ | AK14: 30 | AL14: 960 | AM14: 960 | AO14: =IFERROR(AM14/AI14,"") | AS14: Internal fixed (C14) | AU14: 1 | AV14: 0 | AW14: None (fixed) | AX14: 74.5 | AY14: 89.2 | AZ14: 1197 | BA14: =IF(MAX(AY14,AZ14)=0,"",ROUND(MAX(AY14,AZ14)*3.412,0)) | BB14: 240 | BC14: 178.56 | BD14: 32 | BE14: 2 | BF14: Quad-core Cortex-A57 1.8GHz | BG14: 16384 | BH14: 4093 | BI14: 2K IPv4 / 2K IPv6 | BJ14: 8 x 8 ports | BK14: Lite L3 (static, RIP, PIM-SM/DM, DHCP server) | BL14: No | BN14: Yes (256 streams; not on LAG) | BO14: PTPv2 1-step E2E Transparent Clock | BP14: No | BQ14: Yes | BR14: Yes | BS14: No | BT14: 45 | BU14: Side-to-side | BV14: No | BW14: 29 | BX14: 487900 | BY14: ProSAFE Limited Lifetime HW; Lifetime NBD replacement | BZ14: Cat 3 | CA14: Not listed | CK14: M4250 datasheet DS-M4250-9Nov23 (fw 13.0.4) | CL14: 2026-09-27
A15: GSM4248UX | B15: M4250-40G8XF-PoE++ | C15: M4250 | D15: NETGEAR AV Line | E15: Switch | F15: Access / Edge | G15: AV UI; Engage; IT Web GUI; CLI; SNMP | H15: Active | L15: 2U rack | M15: 2 | N15: Full width | O15: 440 | P15: 350 | Q15: 86.4 | R15: 10.28 | S15: 40 | T15: 0 | U15: 0 | V15: 0 | W15: 0 | X15: 8 | Y15: 0 | Z15: 0 | AA15: 0 | AB15: 0 | AC15: 0 | AD15: 0 | AE15: 0 | AF15: =SUM(S15:AE15) | AI15: 40 | AJ15: 802.3bt Ultra90 PoE++ | AK15: 90 | AL15: 720 | AM15: 2880 | AO15: =IFERROR(AM15/AI15,"") | AS15: 3x internal fixed (C14), RPS/EPS | AU15: 3 | AV15: 0 | AW15: None (fixed) | AX15: 68.5 | AY15: 82.6 | AZ15: 3523 | BA15: =IF(MAX(AY15,AZ15)=0,"",ROUND(MAX(AY15,AZ15)*3.412,0)) | BB15: 240 | BC15: 178.56 | BD15: 32 | BE15: 2 | BF15: Quad-core Cortex-A57 1.8GHz | BG15: 16384 | BH15: 4093 | BI15: 2K IPv4 / 2K IPv6 | BJ15: 8 x 8 ports | BK15: Lite L3 (static, RIP, PIM-SM/DM, DHCP server) | BL15: No | BN15: Yes (256 streams; not on LAG) | BO15: PTPv2 1-step E2E Transparent Clock | BP15: No | BQ15: Yes | BR15: Yes | BS15: No | BT15: 45 | BU15: Side-to-side | BV15: No | BW15: 30 | BX15: 304916 | BY15: ProSAFE Limited Lifetime HW; Lifetime NBD replacement | BZ15: Cat 3 | CA15: Not listed | CK15: M4250 datasheet DS-M4250-9Nov23 (fw 13.0.4) | CL15: 2026-09-27 | CM15: PoE budget 720W (1 PSU) / 1,650W (2 PSU) / 2,880W (3 PSU). Full-PoE power: 912 / 1,998 / 3,523W
A16: MSM4214X | B16: M4250-12M2XF | C16: M4250 | D16: NETGEAR AV Line | E16: Switch | F16: Aggregation | G16: AV UI; Engage; IT Web GUI; CLI; SNMP | H16: Active | L16: 1U rack | M16: 1 | N16: Full width | O16: 440 | P16: 100 | Q16: 43.2 | R16: 1.745 | S16: 0 | T16: 12 | U16: 0 | V16: 0 | W16: 0 | X16: 2 | Y16: 0 | Z16: 0 | AA16: 0 | AB16: 0 | AC16: 0 | AD16: 0 | AE16: 0 | AF16: =SUM(S16:AE16) | AI16: 0 | AJ16: None | AO16: =IFERROR(AM16/AI16,"") | AS16: Internal fixed (C14) | AU16: 1 | AV16: 0 | AW16: None (fixed) | AX16: 14.1 | AY16: 37.9 | BA16: =IF(MAX(AY16,AZ16)=0,"",ROUND(MAX(AY16,AZ16)*3.412,0)) | BB16: 100 | BC16: 74.4 | BD16: 16 | BE16: 2 | BF16: ARM A9 1.25GHz | BG16: 16384 | BH16: 4093 | BI16: 2K IPv4 / 2K IPv6 | BJ16: 8 x 8 ports | BK16: Lite L3 (static, RIP, PIM-SM/DM, DHCP server) | BL16: No | BN16: Yes (256 streams; not on LAG) | BO16: PTPv2 1-step E2E Transparent Clock | BP16: No | BQ16: Yes | BR16: Yes | BS16: No | BT16: 50 | BU16: Side-to-side | BV16: Yes (8x2.5G, no SFP+) | BW16: 28.5 | BX16: 720892 | BY16: ProSAFE Limited Lifetime HW; Lifetime NBD replacement | BZ16: Cat 2 | CA16: Not listed | CK16: M4250 datasheet DS-M4250-9Nov23 (fw 13.0.4) | CL16: 2026-09-27
A17: XSM4216F | B17: M4250-16XF | C17: M4250 | D17: NETGEAR AV Line | E17: Switch | F17: Aggregation | G17: AV UI; Engage; IT Web GUI; CLI; SNMP | H17: Active | L17: 1U rack | M17: 1 | N17: Full width | O17: 440 | P17: 200 | Q17: 43.2 | R17: 2.8 | S17: 0 | T17: 0 | U17: 0 | V17: 0 | W17: 0 | X17: 16 | Y17: 0 | Z17: 0 | AA17: 0 | AB17: 0 | AC17: 0 | AD17: 0 | AE17: 0 | AF17: =SUM(S17:AE17) | AG17: 12 | AH17: 1G SFP only on ports 1-12 | AI17: 0 | AJ17: None | AO17: =IFERROR(AM17/AI17,"") | AS17: Internal fixed (C14) | AU17: 1 | AV17: 0 | AW17: None (fixed) | AX17: 19.27 | AY17: 47.84 | BA17: =IF(MAX(AY17,AZ17)=0,"",ROUND(MAX(AY17,AZ17)*3.412,0)) | BB17: 320 | BC17: 238.08 | BD17: 16 | BE17: 2 | BF17: ARM A9 1.25GHz | BG17: 16384 | BH17: 4093 | BI17: 2K IPv4 / 2K IPv6 | BJ17: 8 x 8 ports | BK17: Lite L3 (static, RIP, PIM-SM/DM, DHCP server) | BL17: No | BN17: Yes (256 streams; not on LAG) | BO17: PTPv2 1-step E2E Transparent Clock | BP17: No | BQ17: Yes | BR17: Yes | BS17: No | BT17: 50 | BU17: Side-to-side | BV17: Yes (8x SFP+) | BW17: 27.44 | BX17: 844633 | BY17: ProSAFE Limited Lifetime HW; Lifetime NBD replacement | BZ17: Cat 2 | CA17: Not listed | CK17: M4250 datasheet DS-M4250-9Nov23 (fw 13.0.4) | CL17: 2026-09-27 | CM17: Weight: 1.74 kg on product page vs 2.80 kg in spec table - verify
A18: GSM4328 | B18: M4350-24G4XF | C18: M4350 | D18: NETGEAR AV and IT | E18: Switch | F18: Access / Edge | G18: AV UI; Engage; IT Web GUI; CLI; SNMP | H18: Active | L18: 1U rack | M18: 1 | N18: Full width | O18: 440 | P18: 400 | Q18: 43.2 | R18: 6.41 | S18: 24 | T18: 0 | U18: 0 | V18: 0 | W18: 0 | X18: 4 | Y18: 0 | Z18: 0 | AA18: 0 | AB18: 0 | AC18: 0 | AD18: 0 | AE18: 0 | AF18: =SUM(S18:AE18) | AI18: 24 | AJ18: 802.3at PoE+ | AK18: 30 | AL18: 648 | AM18: 720 | AN18: 648 | AO18: =IFERROR(AM18/AI18,"") | AS18: Internal fixed + modular slots | AT18: 880 | AU18: 1 | AV18: 1 | AW18: A: APS350W / APS600Wv2 / APS920W / APS2000W | AX18: 32 | AY18: 80 | AZ18: 871.2 | BA18: =IF(MAX(AY18,AZ18)=0,"",ROUND(MAX(AY18,AZ18)*3.412,0)) | BB18: 128 | BC18: 95.23 | BD18: 16 | BE18: 2 | BF18: Quad-core Cortex-A57 1.8GHz | BG18: 16384 | BH18: 4093 | BI18: 2K IPv4 / 2K IPv6 | BK18: Full L3 (static, RIP, OSPF, VRRP, PIM-SM/DM, PBR) | BL18: Yes (NSF) | BM18: 8 | BN18: Yes (exclusive with stacking) | BO18: PTPv2 1-step E2E Transparent Clock | BP18: No | BQ18: Yes | BR18: Yes | BS18: No | BT18: 45 | BU18: Front-to-back | BV18: No (Quiet / Cool modes) | BW18: 33 | BX18: 782376 | BY18: ProSAFE Limited Lifetime HW; Lifetime NBD replacement | BZ18: Cat 3 | CA18: Not listed | CK18: M4350 datasheet DS-M4350-30May25 (fw 14.0) [file: M3450_Datasheet_30May25.pdf] | CL18: 2026-09-27
A19: GSM4352 | B19: M4350-48G4XF | C19: M4350 | D19: NETGEAR AV and IT | E19: Switch | F19: Access / Edge | G19: AV UI; Engage; IT Web GUI; CLI; SNMP | H19: Active | L19: 1U rack | M19: 1 | N19: Full width | O19: 440 | P19: 400 | Q19: 43.2 | R19: 7.19 | S19: 48 | T19: 0 | U19: 0 | V19: 0 | W19: 0 | X19: 4 | Y19: 0 | Z19: 0 | AA19: 0 | AB19: 0 | AC19: 0 | AD19: 0 | AE19: 0 | AF19: =SUM(S19:AE19) | AI19: 48 | AJ19: 802.3at PoE+ | AK19: 30 | AL19: 236 | AM19: 1440 | AN19: 1440 | AO19: =IFERROR(AM19/AI19,"") | AS19: Internal fixed + modular slots | AT19: 550 | AU19: 1 | AV19: 2 | AW19: A: APS350W / APS600Wv2 / APS920W / APS2000W | AX19: 48.5 | AY19: 99 | AZ19: 1618.3 | BA19: =IF(MAX(AY19,AZ19)=0,"",ROUND(MAX(AY19,AZ19)*3.412,0)) | BB19: 176 | BC19: 130.94 | BD19: 32 | BE19: 2 | BF19: Quad-core Cortex-A57 1.8GHz | BG19: 16384 | BH19: 4093 | BI19: 2K IPv4 / 2K IPv6 | BK19: Full L3 (static, RIP, OSPF, VRRP, PIM-SM/DM, PBR) | BL19: Yes (NSF) | BM19: 8 | BN19: Yes (exclusive with stacking) | BO19: PTPv2 1-step E2E Transparent Clock | BP19: No | BQ19: Yes | BR19: Yes | BS19: No | BT19: 45 | BU19: Front-to-back | BV19: No (Quiet / Cool modes) | BW19: 33 | BX19: 623591 | BY19: ProSAFE Limited Lifetime HW; Lifetime NBD replacement | BZ19: Cat 3 | CA19: Not listed | CK19: M4350 datasheet DS-M4350-30May25 (fw 14.0) [file: M3450_Datasheet_30May25.pdf] | CL19: 2026-09-27
A20: MSM4310 | B20: M4350-8M2V | C20: M4350 | D20: NETGEAR AV and IT | E20: Switch | F20: Access / Edge | G20: AV UI; Engage; IT Web GUI; CLI; SNMP | H20: Active | L20: 1U rack | M20: 1 | N20: Half width | O20: 220 | P20: 300 | Q20: 43.2 | R20: 2.9 | S20: 0 | T20: 8 | U20: 0 | V20: 0 | W20: 0 | X20: 0 | Y20: 2 | Z20: 0 | AA20: 0 | AB20: 0 | AC20: 0 | AD20: 0 | AE20: 0 | AF20: =SUM(S20:AE20) | AH20: SFP28 ports 9-10: 10G or 25G only | AI20: 8 | AJ20: 802.3bt Ultra90 PoE++ | AK20: 90 | AL20: 119 | AM20: 551 | AN20: 322 | AO20: =IFERROR(AM20/AI20,"") | AS20: External adapter APS254W (1 incl., 3 DC inputs) | AT20: 254 | AU20: 1 | AV20: 2 | AW20: APS254W (external DC, up to 3 total) | AX20: 61.2 | AY20: 82 | AZ20: 682 | BA20: =IF(MAX(AY20,AZ20)=0,"",ROUND(MAX(AY20,AZ20)*3.412,0)) | BB20: 140 | BC20: 104.16 | BD20: 32 | BE20: 4 | BF20: Quad-core Cortex-A57 1.8GHz | BG20: 16384 | BH20: 4093 | BI20: 2K IPv4 / 2K IPv6 | BK20: Full L3 (static, RIP, OSPF, VRRP, PIM-SM/DM, PBR) | BL20: Yes (NSF) | BM20: 8 | BN20: Yes (exclusive with stacking) | BO20: PTPv2 TC + Boundary/Grandmaster (SMPTE 2059-2, AES67, AES-R16) | BP20: Yes | BQ20: Yes | BR20: Yes | BS20: No | BT20: 45 | BU20: Front-to-back | BV20: No (Quiet / Cool modes) | BW20: 32.2 | BX20: 415986 | BY20: ProSAFE Limited Lifetime HW; Lifetime NBD replacement | BZ20: Cat 3 | CA20: Yes (-TAANES) | CK20: M4350 datasheet DS-M4350-30May25 (fw 14.0) [file: M3450_Datasheet_30May25.pdf] | CL20: 2026-09-27 | CM20: Ships with 1x APS254W. Redundant budget 119W (1+1) or 322W (2+1). Optional PST4310 half-width PSU tray.
A21: MSM4332 | B21: M4350-24M4X4V | C21: M4350 | D21: NETGEAR AV and IT | E21: Switch | F21: Access / Edge | G21: AV UI; Engage; IT Web GUI; CLI; SNMP | H21: Active | L21: 1U rack | M21: 1 | N21: Full width | O21: 440 | P21: 400 | Q21: 43.2 | R21: 7.38 | S21: 0 | T21: 24 | U21: 4 | V21: 0 | W21: 0 | X21: 0 | Y21: 4 | Z21: 0 | AA21: 0 | AB21: 0 | AC21: 0 | AD21: 0 | AE21: 0 | AF21: =SUM(S21:AE21) | AH21: 10G RJ45 ports: 1/2.5/5/10G only (no 100M). SFP28 29-32: 10G or 25G only | AI21: 28 | AJ21: 802.3bt Ultra90 PoE++ | AK21: 90 | AL21: 522 | AM21: 2520 | AN21: 1972 | AO21: =IFERROR(AM21/AI21,"") | AS21: Internal fixed + modular slots | AT21: 800 | AU21: 1 | AV21: 2 | AW21: B: APS600Wv3 / APS1200Wv2 / APS2000Wv2 | AX21: 53 | AY21: 123.4 | AZ21: 2845 | BA21: =IF(MAX(AY21,AZ21)=0,"",ROUND(MAX(AY21,AZ21)*3.412,0)) | BB21: 400 | BC21: 297.6 | BD21: 32 | BE21: 4 | BF21: Quad-core Cortex-A57 1.8GHz | BG21: 16384 | BH21: 4093 | BI21: 2K IPv4 / 2K IPv6 | BK21: Full L3 (static, RIP, OSPF, VRRP, PIM-SM/DM, PBR) | BL21: Yes (NSF) | BM21: 8 | BN21: Yes (exclusive with stacking) | BO21: PTPv2 TC + Boundary/Grandmaster (SMPTE 2059-2, AES67, AES-R16) | BP21: Yes | BQ21: Yes | BR21: Yes | BS21: No | BT21: 45 | BU21: Front-to-back | BV21: No (Quiet / Cool modes) | BW21: 34.8 | BX21: 377861 | BY21: ProSAFE Limited Lifetime HW; Lifetime NBD replacement | BZ21: Cat 3 | CA21: Yes (-TAANES) | CK21: M4350 datasheet DS-M4350-30May25 (fw 14.0) [file: M3450_Datasheet_30May25.pdf] | CL21: 2026-09-27
A22: MSM4352 | B22: M4350-44M4X4V | C22: M4350 | D22: NETGEAR AV and IT | E22: Switch | F22: Access / Edge | G22: AV UI; Engage; IT Web GUI; CLI; SNMP | H22: Active | L22: 1U rack | M22: 1 | N22: Full width | O22: 440 | P22: 400 | Q22: 43.2 | R22: 7.34 | S22: 0 | T22: 44 | U22: 4 | V22: 0 | W22: 0 | X22: 0 | Y22: 4 | Z22: 0 | AA22: 0 | AB22: 0 | AC22: 0 | AD22: 0 | AE22: 0 | AF22: =SUM(S22:AE22) | AH22: 100M only on ports 1-44; 10G RJ45 no 100M. SFP28 49-52: 10G or 25G only | AI22: 48 | AJ22: 802.3bt Ultra90 PoE++ | AK22: 90 | AL22: 194 | AM22: 3314 | AN22: 1794 | AO22: =IFERROR(AM22/AI22,"") | AS22: Internal fixed + modular slots | AT22: 550 | AU22: 1 | AV22: 2 | AW22: A: APS350W / APS600Wv2 / APS920W / APS2000W | AX22: 56.5 | AY22: 133.5 | AZ22: 3857.5 | BA22: =IF(MAX(AY22,AZ22)=0,"",ROUND(MAX(AY22,AZ22)*3.412,0)) | BB22: 500 | BC22: 372 | BD22: 32 | BE22: 2 | BF22: Quad-core Cortex-A57 1.8GHz | BG22: 16384 | BH22: 4093 | BI22: 2K IPv4 / 2K IPv6 | BK22: Full L3 (static, RIP, OSPF, VRRP, PIM-SM/DM, PBR) | BL22: Yes (NSF) | BM22: 8 | BN22: Yes (exclusive with stacking) | BO22: PTPv2 1-step E2E Transparent Clock | BP22: No | BQ22: Yes | BR22: Yes | BS22: No | BT22: 45 | BU22: Front-to-back | BV22: No (Quiet / Cool modes) | BW22: 34 | BX22: 320552 | BY22: ProSAFE Limited Lifetime HW; Lifetime NBD replacement | BZ22: Cat 3 | CA22: Yes (-TAANES) | CK22: M4350 datasheet DS-M4350-30May25 (fw 14.0) [file: M3450_Datasheet_30May25.pdf] | CL22: 2026-09-27 | CM22: Max 3,314W PoE needs 2x APS2000W on 220VAC
A23: MSM4328F | B23: M4350-24F4X | C23: M4350 | D23: NETGEAR AV and IT | E23: Switch | F23: Aggregation / Core | G23: AV UI; Engage; IT Web GUI; CLI; SNMP | H23: Active | L23: 1U rack | M23: 1 | N23: Full width | O23: 440 | P23: 400 | Q23: 43.2 | R23: 7.38 | S23: 0 | T23: 0 | U23: 0 | V23: 0 | W23: 24 | X23: 0 | Y23: 0 | Z23: 0 | AA23: 0 | AB23: 0 | AC23: 0 | AD23: 0 | AE23: 4 | AF23: =SUM(S23:AE23) | AH23: 24x SFP 1G/2.5G only; 4 combo 10GBASE-T / SFP+ (SFP+ side 1G/10G only) | AI23: 0 | AJ23: None | AO23: =IFERROR(AM23/AI23,"") | AS23: Internal fixed + modular slots | AT23: 240 | AU23: 1 | AV23: 1 | AW23: B: APS600Wv3 / APS1200Wv2 / APS2000Wv2 | AX23: 39 | AY23: 115.5 | BA23: =IF(MAX(AY23,AZ23)=0,"",ROUND(MAX(AY23,AZ23)*3.412,0)) | BB23: 200 | BC23: 148.8 | BD23: 32 | BE23: 4 | BF23: Quad-core Cortex-A57 1.8GHz | BG23: 16384 | BH23: 4093 | BI23: 2K IPv4 / 2K IPv6 | BK23: Full L3 (static, RIP, OSPF, VRRP, PIM-SM/DM, PBR) | BL23: Yes (NSF) | BM23: 8 | BN23: Yes (exclusive with stacking) | BO23: PTPv2 TC + Boundary/Grandmaster (SMPTE 2059-2, AES67, AES-R16) | BP23: Yes | BQ23: Yes | BR23: Yes | BS23: No | BT23: 50 | BU23: Front-to-back | BV23: No (Quiet / Cool modes) | BW23: 30 | BX23: 795845 | BY23: ProSAFE Limited Lifetime HW; Lifetime NBD replacement | BZ23: Cat 3 | CA23: Yes (-TAANES) | CK23: M4350 datasheet DS-M4350-30May25 (fw 14.0) [file: M3450_Datasheet_30May25.pdf] | CL23: 2026-09-27 | CM23: Modular slot = RPS only (no PoE)
A24: XSM4316 | B24: M4350-8X8F | C24: M4350 | D24: NETGEAR AV and IT | E24: Switch | F24: Aggregation / Core | G24: AV UI; Engage; IT Web GUI; CLI; SNMP | H24: Active | L24: 1U rack | M24: 1 | N24: Half width | O24: 220 | P24: 400 | Q24: 43.2 | R24: 4.05 | S24: 0 | T24: 0 | U24: 8 | V24: 0 | W24: 0 | X24: 8 | Y24: 0 | Z24: 0 | AA24: 0 | AB24: 0 | AC24: 0 | AD24: 0 | AE24: 0 | AF24: =SUM(S24:AE24) | AH24: 1G on copper 1-8 and SFP+ 9-12 only | AI24: 0 | AJ24: None | AO24: =IFERROR(AM24/AI24,"") | AS24: Internal fixed (C14) | AT24: 240 | AU24: 1 | AV24: 0 | AW24: None (fixed) | AX24: 30.5 | AY24: 81.1 | BA24: =IF(MAX(AY24,AZ24)=0,"",ROUND(MAX(AY24,AZ24)*3.412,0)) | BB24: 320 | BC24: 238.08 | BD24: 32 | BE24: 2 | BF24: Quad-core Cortex-A57 1.8GHz | BG24: 16384 | BH24: 4093 | BI24: 2K IPv4 / 2K IPv6 | BK24: Full L3 (static, RIP, OSPF, VRRP, PIM-SM/DM, PBR) | BL24: Yes (NSF) | BM24: 8 | BN24: Yes (exclusive with stacking) | BO24: PTPv2 1-step E2E Transparent Clock | BP24: No | BQ24: Yes | BR24: Yes | BS24: No | BT24: 50 | BU24: Front-to-back | BV24: No (Quiet / Cool modes) | BW24: 34.43 | BX24: 1101630 | BY24: ProSAFE Limited Lifetime HW; Lifetime NBD replacement | BZ24: Cat 3 | CA24: Not listed | CK24: M4350 datasheet DS-M4350-30May25 (fw 14.0) [file: M3450_Datasheet_30May25.pdf] | CL24: 2026-09-27
A25: XSM4324 | B25: M4350-12X12F | C25: M4350 | D25: NETGEAR AV and IT | E25: Switch | F25: Aggregation / Core | G25: AV UI; Engage; IT Web GUI; CLI; SNMP | H25: Active | L25: 1U rack | M25: 1 | N25: Half width | O25: 220 | P25: 400 | Q25: 43.2 | R25: 4.3 | S25: 0 | T25: 0 | U25: 12 | V25: 0 | W25: 0 | X25: 12 | Y25: 0 | Z25: 0 | AA25: 0 | AB25: 0 | AC25: 0 | AD25: 0 | AE25: 0 | AF25: =SUM(S25:AE25) | AH25: 1G on copper 1-12 and SFP+ 13-20 only | AI25: 0 | AJ25: None | AO25: =IFERROR(AM25/AI25,"") | AS25: Internal fixed (C14) | AT25: 240 | AU25: 1 | AV25: 0 | AW25: None (fixed) | AX25: 34 | AY25: 95.8 | BA25: =IF(MAX(AY25,AZ25)=0,"",ROUND(MAX(AY25,AZ25)*3.412,0)) | BB25: 480 | BC25: 357.12 | BD25: 32 | BE25: 2 | BF25: Quad-core Cortex-A57 1.8GHz | BG25: 16384 | BH25: 4093 | BI25: 2K IPv4 / 2K IPv6 | BK25: Full L3 (static, RIP, OSPF, VRRP, PIM-SM/DM, PBR) | BL25: Yes (NSF) | BM25: 8 | BN25: Yes (exclusive with stacking) | BO25: PTPv2 1-step E2E Transparent Clock | BP25: No | BQ25: Yes | BR25: Yes | BS25: No | BT25: 50 | BU25: Front-to-back | BV25: No (Quiet / Cool modes) | BW25: 34.34 | BX25: 780202 | BY25: ProSAFE Limited Lifetime HW; Lifetime NBD replacement | BZ25: Cat 3 | CA25: Not listed | CK25: M4350 datasheet DS-M4350-30May25 (fw 14.0) [file: M3450_Datasheet_30May25.pdf] | CL25: 2026-09-27
A26: XSM4328CV | B26: M4350-24X4V | C26: M4350 | D26: NETGEAR AV and IT | E26: Switch | F26: Access / Edge | G26: AV UI; Engage; IT Web GUI; CLI; SNMP | H26: Active | L26: 1U rack | M26: 1 | N26: Full width | O26: 440 | P26: 400 | Q26: 43.2 | R26: 6.58 | S26: 0 | T26: 0 | U26: 24 | V26: 0 | W26: 0 | X26: 0 | Y26: 4 | Z26: 0 | AA26: 0 | AB26: 0 | AC26: 0 | AD26: 0 | AE26: 0 | AF26: =SUM(S26:AE26) | AH26: 100M only on ports 1-16. SFP28 25-28: 10G or 25G only | AI26: 24 | AJ26: 802.3at PoE+ | AK26: 30 | AL26: 576 | AM26: 720 | AN26: 576 | AO26: =IFERROR(AM26/AI26,"") | AS26: Internal fixed + modular slots | AT26: 880 | AU26: 1 | AV26: 1 | AW26: A: APS350W / APS600Wv2 / APS920W / APS2000W | AX26: 53.6 | AY26: 119.4 | AZ26: 907.8 | BA26: =IF(MAX(AY26,AZ26)=0,"",ROUND(MAX(AY26,AZ26)*3.412,0)) | BB26: 680 | BC26: 505.92 | BD26: 32 | BE26: 2 | BF26: Quad-core Cortex-A57 1.8GHz | BG26: 16384 | BH26: 4093 | BI26: 2K IPv4 / 2K IPv6 | BK26: Full L3 (static, RIP, OSPF, VRRP, PIM-SM/DM, PBR) | BL26: Yes (NSF) | BM26: 8 | BN26: Yes (exclusive with stacking) | BO26: PTPv2 1-step E2E Transparent Clock | BP26: No | BQ26: Yes | BR26: Yes | BS26: No | BT26: 45 | BU26: Front-to-back | BV26: No (Quiet / Cool modes) | BW26: 34.7 | BX26: 486832 | BY26: ProSAFE Limited Lifetime HW; Lifetime NBD replacement | BZ26: Cat 3 | CA26: Yes (-TAANES) | CK26: M4350 datasheet DS-M4350-30May25 (fw 14.0) [file: M3450_Datasheet_30May25.pdf] | CL26: 2026-09-27
A27: XSM4328FV | B27: M4350-24F4V | C27: M4350 | D27: NETGEAR AV and IT | E27: Switch | F27: Aggregation / Core | G27: AV UI; Engage; IT Web GUI; CLI; SNMP | H27: Active | L27: 1U rack | M27: 1 | N27: Full width | O27: 440 | P27: 400 | Q27: 43.2 | R27: 6.25 | S27: 0 | T27: 0 | U27: 0 | V27: 0 | W27: 0 | X27: 24 | Y27: 4 | Z27: 0 | AA27: 0 | AB27: 0 | AC27: 0 | AD27: 0 | AE27: 0 | AF27: =SUM(S27:AE27) | AH27: 1G on SFP+ 1-16 only. SFP28 25-28: 10G or 25G only | AI27: 0 | AJ27: None | AO27: =IFERROR(AM27/AI27,"") | AS27: Internal fixed + modular slots | AT27: 240 | AU27: 1 | AV27: 1 | AW27: A: APS350W / APS600Wv2 / APS920W / APS2000W | AX27: 45.2 | AY27: 119.3 | BA27: =IF(MAX(AY27,AZ27)=0,"",ROUND(MAX(AY27,AZ27)*3.412,0)) | BB27: 680 | BC27: 505.92 | BD27: 32 | BE27: 2 | BF27: Quad-core Cortex-A57 1.8GHz | BG27: 16384 | BH27: 4093 | BI27: 2K IPv4 / 2K IPv6 | BK27: Full L3 (static, RIP, OSPF, VRRP, PIM-SM/DM, PBR) | BL27: Yes (NSF) | BM27: 8 | BN27: Yes (exclusive with stacking) | BO27: PTPv2 1-step E2E Transparent Clock | BP27: No | BQ27: Yes | BR27: Yes | BS27: No | BT27: 50 | BU27: Front-to-back | BV27: No (Quiet / Cool modes) | BW27: 34.2 | BX27: 778741 | BY27: ProSAFE Limited Lifetime HW; Lifetime NBD replacement | BZ27: Cat 3 | CA27: Not listed | CK27: M4350 datasheet DS-M4350-30May25 (fw 14.0) [file: M3450_Datasheet_30May25.pdf] | CL27: 2026-09-27 | CM27: Modular slot = RPS only (no PoE)
A28: XSM4340CV | B28: M4350-36X4V | C28: M4350 | D28: NETGEAR AV and IT | E28: Switch | F28: Access / Edge | G28: AV UI; Engage; IT Web GUI; CLI; SNMP | H28: Active | L28: 1U rack | M28: 1 | N28: Full width | O28: 440 | P28: 400 | Q28: 43.2 | R28: 7.33 | S28: 0 | T28: 0 | U28: 36 | V28: 0 | W28: 0 | X28: 0 | Y28: 4 | Z28: 0 | AA28: 0 | AB28: 0 | AC28: 0 | AD28: 0 | AE28: 0 | AF28: =SUM(S28:AE28) | AH28: 100M only on ports 1-28 | AI28: 36 | AJ28: 802.3bt Ultra90 PoE++ | AK28: 90 | AL28: 280 | AM28: 1760 | AN28: 280 | AO28: =IFERROR(AM28/AI28,"") | AS28: Internal fixed + modular slots | AT28: 750 | AU28: 1 | AV28: 1 | AW28: B: APS600Wv3 / APS1200Wv2 / APS2000Wv2 | AX28: 59.3 | AY28: 148 | AZ28: 2071.4 | BA28: =IF(MAX(AY28,AZ28)=0,"",ROUND(MAX(AY28,AZ28)*3.412,0)) | BB28: 920 | BC28: 684.48 | BD28: 64 | BE28: 4 | BF28: Quad-core Cortex-A57 1.8GHz | BG28: 16384 | BH28: 4093 | BI28: 2K IPv4 / 2K IPv6 | BK28: Full L3 (static, RIP, OSPF, VRRP, PIM-SM/DM, PBR) | BL28: Yes (NSF) | BM28: 8 | BN28: Yes (exclusive with stacking) | BO28: PTPv2 1-step E2E Transparent Clock | BP28: No | BQ28: Yes | BR28: Yes | BS28: No | BT28: 45 | BU28: Front-to-back | BV28: No (Quiet / Cool modes) | BW28: 32.1 | BX28: 292505 | BY28: ProSAFE Limited Lifetime HW; Lifetime NBD replacement | BZ28: Cat 4 | CA28: Not listed | CK28: M4350 datasheet DS-M4350-30May25 (fw 14.0) [file: M3450_Datasheet_30May25.pdf] | CL28: 2026-09-27
A29: XSM4340V | B29: M4350-24X8F8V | C29: M4350 | D29: NETGEAR AV and IT | E29: Switch | F29: Access / Edge | G29: AV UI; Engage; IT Web GUI; CLI; SNMP | H29: Active | L29: 1U rack | M29: 1 | N29: Full width | O29: 440 | P29: 400 | Q29: 43.2 | R29: 7.24 | S29: 0 | T29: 0 | U29: 24 | V29: 0 | W29: 0 | X29: 8 | Y29: 8 | Z29: 0 | AA29: 0 | AB29: 0 | AC29: 0 | AD29: 0 | AE29: 0 | AF29: =SUM(S29:AE29) | AH29: 1G on SFP+ 25-28 only. SFP28 33-40: 10G or 25G per 4-port block | AI29: 24 | AJ29: 802.3bt Ultra90 PoE++ | AK29: 90 | AL29: 290 | AM29: 1770 | AN29: 290 | AO29: =IFERROR(AM29/AI29,"") | AS29: Internal fixed + modular slots | AT29: 750 | AU29: 1 | AV29: 1 | AW29: B: APS600Wv3 / APS1200Wv2 / APS2000Wv2 | AX29: 53.4 | AY29: 151.8 | AZ29: 2057.3 | BA29: =IF(MAX(AY29,AZ29)=0,"",ROUND(MAX(AY29,AZ29)*3.412,0)) | BB29: 1040 | BC29: 773.76 | BD29: 64 | BE29: 4 | BF29: Quad-core Cortex-A57 1.8GHz | BG29: 16384 | BH29: 4093 | BI29: 2K IPv4 / 2K IPv6 | BK29: Full L3 (static, RIP, OSPF, VRRP, PIM-SM/DM, PBR) | BL29: Yes (NSF) | BM29: 8 | BN29: Yes (exclusive with stacking) | BO29: PTPv2 1-step E2E Transparent Clock | BP29: No | BQ29: Yes | BR29: Yes | BS29: No | BT29: 45 | BU29: Front-to-back | BV29: No (Quiet / Cool modes) | BW29: 32.6 | BX29: 386078 | BY29: ProSAFE Limited Lifetime HW; Lifetime NBD replacement | BZ29: Cat 4 | CA29: Yes (-TAANES) | CK29: M4350 datasheet DS-M4350-30May25 (fw 14.0) [file: M3450_Datasheet_30May25.pdf] | CL29: 2026-09-27
A30: XSM4340FV | B30: M4350-32F8V | C30: M4350 | D30: NETGEAR AV and IT | E30: Switch | F30: Aggregation / Core | G30: AV UI; Engage; IT Web GUI; CLI; SNMP | H30: Active | L30: 1U rack | M30: 1 | N30: Full width | O30: 440 | P30: 400 | Q30: 43.2 | R30: 6.95 | S30: 0 | T30: 0 | U30: 0 | V30: 0 | W30: 0 | X30: 32 | Y30: 8 | Z30: 0 | AA30: 0 | AB30: 0 | AC30: 0 | AD30: 0 | AE30: 0 | AF30: =SUM(S30:AE30) | AH30: 1G on SFP+ 1-28 only. SFP28 33-40: 10G or 25G per 4-port block | AI30: 0 | AJ30: None | AO30: =IFERROR(AM30/AI30,"") | AS30: Internal fixed + modular slots | AT30: 420 | AU30: 1 | AV30: 1 | AW30: B: APS600Wv3 / APS1200Wv2 / APS2000Wv2 | AX30: 42.6 | AY30: 156.4 | BA30: =IF(MAX(AY30,AZ30)=0,"",ROUND(MAX(AY30,AZ30)*3.412,0)) | BB30: 1040 | BC30: 773.76 | BD30: 64 | BE30: 4 | BF30: Quad-core Cortex-A57 1.8GHz | BG30: 16384 | BH30: 4093 | BI30: 2K IPv4 / 2K IPv6 | BK30: Full L3 (static, RIP, OSPF, VRRP, PIM-SM/DM, PBR) | BL30: Yes (NSF) | BM30: 8 | BN30: Yes (exclusive with stacking) | BO30: PTPv2 1-step E2E Transparent Clock | BP30: No | BQ30: Yes | BR30: Yes | BS30: No | BT30: 50 | BU30: Front-to-back | BV30: No (Quiet / Cool modes) | BW30: 32.7 | BX30: 582420 | BY30: ProSAFE Limited Lifetime HW; Lifetime NBD replacement | BZ30: Cat 4 | CA30: Yes (-TAANES) | CK30: M4350 datasheet DS-M4350-30May25 (fw 14.0) [file: M3450_Datasheet_30May25.pdf] | CL30: 2026-09-27 | CM30: Modular slot = RPS only (no PoE)
A31: VSM4320C | B31: M4350-16V4C | C31: M4350 | D31: NETGEAR AV and IT | E31: Switch | F31: Aggregation / Core | G31: AV UI; Engage; IT Web GUI; CLI; SNMP | H31: Active | L31: 1U rack | M31: 1 | N31: Full width | O31: 440 | P31: 400 | Q31: 43.2 | R31: 7.15 | S31: 0 | T31: 0 | U31: 0 | V31: 0 | W31: 0 | X31: 0 | Y31: 16 | Z31: 4 | AA31: 0 | AB31: 0 | AC31: 0 | AD31: 0 | AE31: 0 | AF31: =SUM(S31:AE31) | AH31: SFP28: 10G or 25G per 4-port block, no stacking on SFP28. QSFP28: 40/100G or 4x25G breakout | AI31: 0 | AJ31: None | AO31: =IFERROR(AM31/AI31,"") | AS31: Internal fixed + modular slots | AT31: 420 | AU31: 1 | AV31: 1 | AW31: B: APS600Wv3 / APS1200Wv2 / APS2000Wv2 | AX31: 60.4 | AY31: 143.4 | BA31: =IF(MAX(AY31,AZ31)=0,"",ROUND(MAX(AY31,AZ31)*3.412,0)) | BB31: 1600 | BC31: 1190.4 | BD31: 256 | BE31: 4 | BF31: Quad-core Cortex-A57 1.8GHz | BG31: 16384 | BH31: 4093 | BI31: 2K IPv4 / 2K IPv6 | BK31: Full L3 (static, RIP, OSPF, VRRP, PIM-SM/DM, PBR) | BL31: Yes (NSF) | BM31: 8 | BN31: Yes (exclusive with stacking) | BO31: PTPv2 TC + Boundary/Grandmaster (SMPTE 2059-2, AES67, AES-R16) | BP31: Yes | BQ31: Yes | BR31: Yes | BS31: No | BT31: 50 | BU31: Front-to-back | BV31: No (Quiet / Cool modes) | BW31: 36.4 | BX31: 518782 | BY31: ProSAFE Limited Lifetime HW; Lifetime NBD replacement | BZ31: Cat 4 | CA31: Yes (-TAANES) | CK31: M4350 datasheet DS-M4350-30May25 (fw 14.0) [file: M3450_Datasheet_30May25.pdf] | CL31: 2026-09-27 | CM31: Modular slot = RPS only (no PoE)
A32: XSM4344C | B32: M4350-40X4C | C32: M4350 | D32: NETGEAR AV and IT | E32: Switch | F32: Access / Edge | G32: AV UI; Engage; IT Web GUI; CLI; SNMP | H32: Active | L32: 1U rack | M32: 1 | N32: Full width | O32: 440 | P32: 400 | Q32: 43.2 | R32: 7.76 | S32: 0 | T32: 0 | U32: 40 | V32: 0 | W32: 0 | X32: 0 | Y32: 0 | Z32: 4 | AA32: 0 | AB32: 0 | AC32: 0 | AD32: 0 | AE32: 0 | AF32: =SUM(S32:AE32) | AH32: 10G RJ45: no 100M on any port. QSFP28: 40/100G or 4x25G breakout | AI32: 40 | AJ32: 802.3bt Ultra90 PoE++ | AK32: 90 | AL32: 196 | AM32: 1676 | AN32: 196 | AO32: =IFERROR(AM32/AI32,"") | AS32: Internal fixed + modular slots | AT32: 750 | AU32: 1 | AV32: 1 | AW32: B: APS600Wv3 / APS1200Wv2 / APS2000Wv2 | AX32: 98.8 | AY32: 200.4 | AZ32: 2018.3 | BA32: =IF(MAX(AY32,AZ32)=0,"",ROUND(MAX(AY32,AZ32)*3.412,0)) | BB32: 1600 | BC32: 1190.4 | BD32: 256 | BE32: 4 | BF32: Quad-core Cortex-A57 1.8GHz | BG32: 16384 | BH32: 4093 | BI32: 2K IPv4 / 2K IPv6 | BK32: Full L3 (static, RIP, OSPF, VRRP, PIM-SM/DM, PBR) | BL32: Yes (NSF) | BM32: 8 | BN32: Yes (exclusive with stacking) | BO32: PTPv2 TC + Boundary/Grandmaster (SMPTE 2059-2, AES67, AES-R16) | BP32: Yes | BQ32: Yes | BR32: Yes | BS32: No | BT32: 45 | BU32: Front-to-back | BV32: No (Quiet / Cool modes) | BW32: 34.1 | BX32: 229375 | BY32: ProSAFE Limited Lifetime HW; Lifetime NBD replacement | BZ32: Cat 4 | CA32: Yes (-TAANES) | CK32: M4350 datasheet DS-M4350-30May25 (fw 14.0) [file: M3450_Datasheet_30May25.pdf] | CL32: 2026-09-27
A33: XSM4344FC | B33: M4350-40F4C | C33: M4350 | D33: NETGEAR AV and IT | E33: Switch | F33: Aggregation / Core | G33: AV UI; Engage; IT Web GUI; CLI; SNMP | H33: Active | L33: 1U rack | M33: 1 | N33: Full width | O33: 440 | P33: 400 | Q33: 43.2 | R33: 7.38 | S33: 0 | T33: 0 | U33: 0 | V33: 0 | W33: 0 | X33: 40 | Y33: 0 | Z33: 4 | AA33: 0 | AB33: 0 | AC33: 0 | AD33: 0 | AE33: 0 | AF33: =SUM(S33:AE33) | AH33: SFP+ 1-40: 1G or 10G only. QSFP28: 40/100G or 4x25G breakout | AI33: 0 | AJ33: None | AO33: =IFERROR(AM33/AI33,"") | AS33: Internal fixed + modular slots | AT33: 420 | AU33: 1 | AV33: 1 | AW33: B: APS600Wv3 / APS1200Wv2 / APS2000Wv2 | AX33: 65 | AY33: 213.6 | BA33: =IF(MAX(AY33,AZ33)=0,"",ROUND(MAX(AY33,AZ33)*3.412,0)) | BB33: 1600 | BC33: 1190.4 | BD33: 256 | BE33: 4 | BF33: Quad-core Cortex-A57 1.8GHz | BG33: 16384 | BH33: 4093 | BI33: 2K IPv4 / 2K IPv6 | BK33: Full L3 (static, RIP, OSPF, VRRP, PIM-SM/DM, PBR) | BL33: Yes (NSF) | BM33: 8 | BN33: Yes (exclusive with stacking) | BO33: PTPv2 TC + Boundary/Grandmaster (SMPTE 2059-2, AES67, AES-R16) | BP33: Yes | BQ33: Yes | BR33: Yes | BS33: No | BT33: 50 | BU33: Front-to-back | BV33: No (Quiet / Cool modes) | BW33: 34 | BX33: 380163 | BY33: ProSAFE Limited Lifetime HW; Lifetime NBD replacement | BZ33: Cat 4 | CA33: Yes (-TAANES) | CK33: M4350 datasheet DS-M4350-30May25 (fw 14.0) [file: M3450_Datasheet_30May25.pdf] | CL33: 2026-09-27 | CM33: Modular slot = RPS only (no PoE)
A34: PR460X | B34: PR460X Pro Router | C34: PR460X | D34: NETGEAR AV / Insight Pro | E34: Router | F34: Gateway / Router | G34: Insight (cloud) OR Engage - not both; Domotz | H34: Active | L34: 1U rack (reversible ears) | M34: 1 | N34: Full width | O34: 440 | P34: 100 | Q34: 43.2 | R34: 1.513 | S34: 0 | T34: 4 | U34: 1 | V34: 0 | W34: 0 | X34: 1 | Y34: 0 | Z34: 0 | AA34: 0 | AB34: 0 | AC34: 0 | AD34: 0 | AE34: 0 | AF34: =SUM(S34:AE34) | AH34: 1x 10G multi-gig (WAN/LAN configurable), 1x 2.5G WAN, 3x 2.5G LAN, 1x 10G SFP+ LAN | AI34: 0 | AJ34: None | AO34: =IFERROR(AM34/AI34,"") | AS34: Internal AC 100-240V, 1.3A | AU34: 1 | AV34: 0 | AW34: None (fixed) | BA34: =IF(MAX(AY34,AZ34)=0,"",ROUND(MAX(AY34,AZ34)*3.412,0)) | BH34: 32 | BK34: NAT router; static, RIPv1/v2; 32 DHCP servers | BL34: No | BN34: No | BP34: No | BR34: Yes (Engage v2) | BS34: Yes | BT34: 40 | BY34: Enterprise Limited Lifetime HW | BZ34: Sprint / Overdrive (SKUs not in datasheet) | CA34: Not listed | CB34: 4-yr Insight subscription | CC34: 2 (dual WAN failover / load balancing) | CD34: 2.4 Gbps (2.5G WAN) / 9.4 Gbps (10G WAN) | CE34: IPSec S2S 30 tunnels; IPSec/OpenVPN/WireGuard client 100 each; S2S 4.42/8.92 Gbps, client 500 Mbps | CF34: 2000 | CK34: PR460X datasheet NG_DS_AV_PR460X-042926 | CL34: 2026-09-27 | CM34: Concurrent connections: 60,000 (spec table) vs 250,000 (features table) - verify. Optional Exium security license (SEC-PR460X-xx), Insight path only.
A35: WBE718 | B35: WBE718 WiFi 7 AP | C35: WBE7xx | D35: Insight Pro WiFi | E35: Access Point | F35: Wireless AP (indoor) | G35: Insight (cloud / app) | H35: Active | L35: Wall / ceiling | N35: Ceiling/Wall | O35: 157 | P35: 157 | Q35: 40 | R35: 0.69 | S35: 0 | T35: 1 | U35: 0 | V35: 0 | W35: 0 | X35: 0 | Y35: 0 | Z35: 0 | AA35: 0 | AB35: 0 | AC35: 0 | AD35: 0 | AE35: 0 | AF35: =SUM(S35:AE35) | AH35: 1x 2.5G PoE PD uplink | AI35: 0 | AJ35: PD | AO35: =IFERROR(AM35/AI35,"") | AP35: 25 | AQ35: 802.3at (af = reduced: -50% 2.4G, -25% 5G, no 6G) | AR35: 2.5G | AS35: PoE or 12V/2.5A adapter (not incl.) | AV35: 0 | AW35: None | BA35: =IF(MAX(AY35,AZ35)=0,"",ROUND(MAX(AY35,AZ35)*3.412,0)) | BR35: Yes (select APs, Engage v2) | BS35: Yes | BT35: 40 | BY35: Enterprise Limited Lifetime HW | BZ35: SPR-/DRV-WBE718 | CA35: Not listed | CB35: 4-yr Insight subscription | CG35: WiFi 7 (802.11be) tri-band | CH35: 2x2 per band (6 streams) | CI35: 9.4 | CJ35: 8 | CK35: WBE718 datasheet DS-WBE718_02Apr26 | CL35: 2026-09-27 | CM35: Weight shown as 0.69 kg (2.09 lb) - lb value inconsistent, verify. Engage support per PR460X datasheet ('select APs') - confirm model list.
A36: WBE758 | B36: WBE758 WiFi 7 AP | C36: WBE7xx | D36: Insight Pro WiFi | E36: Access Point | F36: Wireless AP (indoor) | G36: Insight (cloud / app) | H36: Active | L36: Wall / ceiling | N36: Ceiling/Wall | O36: 172 | P36: 172 | Q36: 44 | R36: 0.95 | S36: 0 | T36: 0 | U36: 1 | V36: 0 | W36: 0 | X36: 0 | Y36: 0 | Z36: 0 | AA36: 0 | AB36: 0 | AC36: 0 | AD36: 0 | AE36: 0 | AF36: =SUM(S36:AE36) | AH36: 1x 10G PoE++ PD uplink | AI36: 0 | AJ36: PD | AO36: =IFERROR(AM36/AI36,"") | AP36: 39 | AQ36: 802.3bt (at = reduced: -50% 2.4G, -25% 5G/6G; af not supported) | AR36: 10G | AS36: PoE or 12V/3.5A adapter (not incl.) | AV36: 0 | AW36: None | BA36: =IF(MAX(AY36,AZ36)=0,"",ROUND(MAX(AY36,AZ36)*3.412,0)) | BR36: Yes (select APs, Engage v2) | BS36: Yes | BT36: 40 | BY36: Enterprise Limited Lifetime HW | BZ36: SPR-/DRV-WBE758 | CA36: Not listed | CB36: 4-yr Insight subscription | CG36: WiFi 7 (802.11be) tri-band | CH36: 4x4 per band (12 streams) | CI36: 18.4 | CJ36: 8 | CK36: WBE758 datasheet D-WBE758_29Jan24 | CL36: 2026-09-27 | CM36: Datasheet intro says 7.8 Gbps, spec table 18.4 Gbps - verify. 2.4GHz listed as 802.11b/g/n/ax (no be).

Sheet SKUs
A1: Orderable SKUs by Region
A2: Product_ID links to Products. Add every orderable variant here (regional, TAA, bundles).
A4: Product_ID | B4: Model_Name | C4: Orderable_SKU | D4: Region | E4: Power_Cord | F4: TAA_Compliant | G4: Notes
A5: GSM4210PD | B5: M4250-9G1F-PoE+ | C5: GSM4210PD-100NAS | D5: Americas | E5: Region cord | F5: No
A6: GSM4210PD | B6: M4250-9G1F-PoE+ | C6: GSM4210PD-100EUS | D6: Europe | E6: Region cord | F6: No
A7: GSM4210PD | B7: M4250-9G1F-PoE+ | C7: GSM4210PD-100INS | D7: India | E7: Region cord | F7: No
A8: GSM4210PD | B8: M4250-9G1F-PoE+ | C8: GSM4210PD-100JPS | D8: Japan | E8: Region cord | F8: No
A9: GSM4210PD | B9: M4250-9G1F-PoE+ | C9: GSM4210PD-100KOS | D9: South Korea | E9: Region cord | F9: No
A10: GSM4210PD | B10: M4250-9G1F-PoE+ | C10: GSM4210PD-100TWS | D10: Taiwan | E10: Region cord | F10: No
A11: GSM4210PD | B11: M4250-9G1F-PoE+ | C11: GSM4210PD-100UKS | D11: Hong Kong | E11: Region cord | F11: No
A12: GSM4210PD | B12: M4250-9G1F-PoE+ | C12: GSM4210PD-100AUS | D12: Australia | E12: Region cord | F12: No
A13: GSM4210PD | B13: M4250-9G1F-PoE+ | C13: GSM4210PD-100PRS | D13: China | E13: Region cord | F13: No
A14: GSM4210PD | B14: M4250-9G1F-PoE+ | C14: GSM4210PD-100PES | D14: Other APAC | E14: Region cord | F14: No
A15: GSM4210PX | B15: M4250-8G2XF-PoE+ | C15: GSM4210PX-100NAS | D15: Americas | E15: Region cord | F15: No
A16: GSM4210PX | B16: M4250-8G2XF-PoE+ | C16: GSM4210PX-100EUS | D16: Europe | E16: Region cord | F16: No
... A141: WBE758 | B141: WBE758 WiFi 7 AP | C141: WBE758-111APS | D141: Asia Pacific | E141: Adapter not incl. | F141: No

Sheet Accessories
A1: Accessories, PSUs, Optics, Cables, Licenses & Support
A2: Base_Model groups variants (e.g. cord options). Compatibility sheet maps Base_Model to products.
A4: Orderable_SKU | B4: Base_Model | C4: Category | D4: Description | E4: Form_Factor | F4: Speed_Gbps | G4: Media | H4: Connector | I4: Reach_m | J4: Fiber_Notes | K4: Output_W_110VAC | L4: Output_W_220VAC | M4: Power_Cord | N4: Term_Months | O4: Warranty | P4: Source | Q4: Notes
A5: AGM731F | B5: AGM731F | C5: Optic | D5: 1000BASE-SX SFP, multimode | E5: SFP | F5: 1 | G5: MMF | H5: LC duplex | I5: 550 | J5: OM1/OM2 275m; OM3 550m; OM4 1,000m | O5: 5 yr | P5: M4250 + M4350 datasheets
A6: AGM732F | B6: AGM732F | C6: Optic | D6: 1000BASE-LX SFP, single mode | E6: SFP | F6: 1 | G6: SMF | H6: LC duplex | I6: 10000 | J6: OS 9/125um | O6: 5 yr | P6: M4250 + M4350 datasheets
A7: AGM734-10000S | B7: AGM734 | C7: Optic | D7: 1000BASE-T RJ45 SFP (1000 Mbps full duplex only) | E7: SFP | F7: 1 | G7: Copper | H7: RJ45 | I7: 100 | J7: Cat5 or better | O7: 5 yr | P7: M4250 + M4350 datasheets | Q7: M4250-16XF: ports 1-12 only
A8: AXM761-10000S | B8: AXM761 | C8: Optic | D8: 10GBASE-SR SFP+, multimode | E8: SFP+ | F8: 10 | G8: MMF | H8: LC duplex | I8: 300 | J8: OM3/OM4 300m; OM1/OM2 33m | O8: 5 yr | P8: M4250 + M4350 datasheets
A9: AXM761P10-10000S | B9: AXM761 | C9: Optic | D9: 10GBASE-SR SFP+, pack of 10 | E9: SFP+ | F9: 10 | G9: MMF | H9: LC duplex | I9: 300 | J9: OM3/OM4 300m; OM1/OM2 33m | O9: 5 yr | P9: M4250 + M4350 datasheets | Q9: Qty 10 per SKU
A10: AXM762-10000S | B10: AXM762 | C10: Optic | D10: 10GBASE-LR SFP+, single mode | E10: SFP+ | F10: 10 | G10: SMF | H10: LC duplex | I10: 10000 | J10: OS 9/125um | O10: 5 yr | P10: M4250 + M4350 datasheets
A11: AXM762P10-10000S | B11: AXM762 | C11: Optic | D11: 10GBASE-LR SFP+, pack of 10 | E11: SFP+ | F11: 10 | G11: SMF | H11: LC duplex | I11: 10000 | J11: OS 9/125um | O11: 5 yr | P11: M4250 + M4350 datasheets | Q11: Qty 10 per SKU
A12: AXM763-10000S | B12: AXM763 | C12: Optic | D12: 10GBASE-LRM SFP+, multimode (802.3aq) | E12: SFP+ | F12: 10 | G12: MMF | H12: LC duplex | I12: 165 | J12: OM3/OM4 165m; OM1/OM2 100m | O12: 5 yr | P12: M4250 + M4350 datasheets
A13: AXM764-10000S | B13: AXM764 | C13: Optic | D13: 10GBASE-LR LITE SFP+, single mode | E13: SFP+ | F13: 10 | G13: SMF | H13: LC duplex | I13: 2000 | J13: OS 9/125um | O13: 5 yr | P13: M4250 + M4350 datasheets
A14: AXM765-20000S | B14: AXM765 | C14: Optic | D14: 10GBASE-T RJ45 SFP+ | E14: SFP+ | F14: 10 | G14: Copper | H14: RJ45 | I14: 80 | J14: Cat6a or better | O14: 5 yr | P14: M4250 + M4350 datasheets
A15: AXC761-10000S | B15: AXC761 | C15: DAC | D15: 10G SFP+ DAC 1m, passive copper | E15: SFP+ | F15: 10 | G15: DAC passive | H15: SFP+ | I15: 1 | O15: 5 yr | P15: M4250 + M4350 datasheets
A16: AXC763-10000S | B16: AXC763 | C16: DAC | D16: 10G SFP+ DAC 3m, passive copper | E16: SFP+ | F16: 10 | G16: DAC passive | H16: SFP+ | I16: 3 | O16: 5 yr | P16: M4250 + M4350 datasheets
A17: AXC765-10000S | B17: AXC765 | C17: DAC | D17: 10G SFP+ DAC 5m, active copper | E17: SFP+ | F17: 10 | G17: DAC active | H17: SFP+ | I17: 5 | O17: 5 yr | P17: M4250 + M4350 datasheets
A18: AXC767-10000S | B18: AXC767 | C18: DAC | D18: 10G SFP+ DAC 7m, active copper | E18: SFP+ | F18: 10 | G18: DAC active | H18: SFP+ | I18: 7 | O18: 5 yr | P18: M4250 + M4350 datasheets
A19: AXC7610-10000S | B19: AXC7610 | C19: DAC | D19: 10G SFP+ DAC 10m, active copper | E19: SFP+ | F19: 10 | G19: DAC active | H19: SFP+ | I19: 10 | O19: 5 yr | P19: M4250 + M4350 datasheets
A20: AXC7615-10000S | B20: AXC7615 | C20: AOC | D20: 10G SFP+ 15m, fiber (AOC) | E20: SFP+ | F20: 10 | G20: AOC | H20: SFP+ | I20: 15 | O20: 5 yr | P20: M4250 + M4350 datasheets
A21: AXC7620-10000S | B21: AXC7620 | C21: AOC | D21: 10G SFP+ 20m, fiber (AOC) | E21: SFP+ | F21: 10 | G21: AOC | H21: SFP+ | I21: 20 | O21: 5 yr | P21: M4250 + M4350 datasheets
A22: APS254W-10000S | B22: APS254W | C22: Power Adapter | D22: 254W external power adapter (C14, no cord) | H22: C14 | K22: 254 | L22: 254 | M22: None | O22: 2 yr | P22: M4350 datasheet DS-M4350-30May25 (fw 14.0) [file: M3450_Datasheet_30May25.pdf] | Q22: For M4350-8M2V and M4250-8G2XF-PoE+
A23: APS350W-100NES | B23: APS350W | C23: PSU Module | D23: 350W modular PSU | H23: C14 | K23: 350 | L23: 350 | M23: NA/UK/EU cords | O23: 5 yr | P23: M4350 datasheet DS-M4350-30May25 (fw 14.0) [file: M3450_Datasheet_30May25.pdf] | Q23: PSU group A
A24: APS350W-100AJS | B24: APS350W | C24: PSU Module | D24: 350W modular PSU | H24: C14 | K24: 350 | L24: 350 | M24: JP/AU cords | O24: 5 yr | P24: M4350 datasheet DS-M4350-30May25 (fw 14.0) [file: M3450_Datasheet_30May25.pdf] | Q24: PSU group A
A25: APS350W-10000S | B25: APS350W | C25: PSU Module | D25: 350W modular PSU | H25: C14 | K25: 350 | L25: 350 | M25: No cord | O25: 5 yr | P25: M4350 datasheet DS-M4350-30May25 (fw 14.0) [file: M3450_Datasheet_30May25.pdf] | Q25: PSU group A
A26: APS600W-200NES | B26: APS600Wv2 | C26: PSU Module | D26: 600W modular PSU (v2) | H26: C14 | K26: 600 | L26: 600 | M26: NA/UK/EU cords | O26: 5 yr | P26: M4350 datasheet DS-M4350-30May25 (fw 14.0) [file: M3450_Datasheet_30May25.pdf] | Q26: PSU group A
A27: APS600W-200AJS | B27: APS600Wv2 | C27: PSU Module | D27: 600W modular PSU (v2) | H27: C14 | K27: 600 | L27: 600 | M27: JP/AU cords | O27: 5 yr | P27: M4350 datasheet DS-M4350-30May25 (fw 14.0) [file: M3450_Datasheet_30May25.pdf] | Q27: PSU group A
A28: APS600W-20000S | B28: APS600Wv2 | C28: PSU Module | D28: 600W modular PSU (v2) | H28: C14 | K28: 600 | L28: 600 | M28: No cord | O28: 5 yr | P28: M4350 datasheet DS-M4350-30May25 (fw 14.0) [file: M3450_Datasheet_30May25.pdf] | Q28: PSU group A
A29: APS920W-100NES | B29: APS920W | C29: PSU Module | D29: 920W modular PSU | H29: C14 | K29: 920 | L29: 920 | M29: NA/UK/EU cords | O29: 5 yr | P29: M4350 datasheet DS-M4350-30May25 (fw 14.0) [file: M3450_Datasheet_30May25.pdf] | Q29: PSU group A
A30: APS920W-100AJS | B30: APS920W | C30: PSU Module | D30: 920W modular PSU | H30: C14 | K30: 920 | L30: 920 | M30: JP/AU cords | O30: 5 yr | P30: M4350 datasheet DS-M4350-30May25 (fw 14.0) [file: M3450_Datasheet_30May25.pdf] | Q30: PSU group A
A31: APS920W-10000S | B31: APS920W | C31: PSU Module | D31: 920W modular PSU | H31: C14 | K31: 920 | L31: 920 | M31: No cord | O31: 5 yr | P31: M4350 datasheet DS-M4350-30May25 (fw 14.0) [file: M3450_Datasheet_30May25.pdf] | Q31: PSU group A
A32: APS2000W-100NES | B32: APS2000W | C32: PSU Module | D32: 2,000W modular PSU (1,000W @110V) | H32: C14 | K32: 1000 | L32: 2000 | M32: NA/UK/EU cords | O32: 5 yr | P32: M4350 datasheet DS-M4350-30May25 (fw 14.0) [file: M3450_Datasheet_30May25.pdf] | Q32: PSU group A
A33: APS2000W-100AJS | B33: APS2000W | C33: PSU Module | D33: 2,000W modular PSU (1,000W @110V) | H33: C14 | K33: 1000 | L33: 2000 | M33: JP/AU cords | O33: 5 yr | P33: M4350 datasheet DS-M4350-30May25 (fw 14.0) [file: M3450_Datasheet_30May25.pdf] | Q33: PSU group A
... A43: APS2000W-20000S | B43: APS2000Wv2 | C43: PSU Module | D43: 2,000W modular PSU v2 (1,000W @110V) | H43: C14 | K43: 1000 | L43: 2000 | M43: No cord | O43: 5 yr | P43: M4350 datasheet DS-M4350-30May25 (fw 14.0) [file: M3450_Datasheet_30May25.pdf] | Q43: PSU group B
A44: PST4310-10000S | B44: PST4310 | C44: PSU Tray | D44: Half-width PSU tray for M4350-8M2V (holds 2x APS254W) | P44: M4350 datasheet DS-M4350-30May25 (fw 14.0) [file: M3450_Datasheet_30May25.pdf]
A45: SEC-PR460X-01 | B45: SEC-PR460X | C45: License | D45: Exium security license - monthly | N45: 1 | P45: PR460X datasheet NG_DS_AV_PR460X-042926 | Q45: SKUs marked WIP in datasheet
A46: SEC-PR460X-12 | B46: SEC-PR460X | C46: License | D46: Exium security license - 1 year | N46: 12 | P46: PR460X datasheet NG_DS_AV_PR460X-042926 | Q46: SKUs marked WIP in datasheet
A47: SEC-PR460X-36 | B47: SEC-PR460X | C47: License | D47: Exium security license - 3 year | N47: 36 | P47: PR460X datasheet NG_DS_AV_PR460X-042926 | Q47: SKUs marked WIP in datasheet
A48: SEC-PR460X-60 | B48: SEC-PR460X | C48: License | D48: Exium security license - 5 year | N48: 60 | P48: PR460X datasheet NG_DS_AV_PR460X-042926 | Q48: SKUs marked WIP in datasheet
A49: PSB0304-10000S | B49: PSB0304 | C49: Service | D49: Remote installation setup & config (2-hr appointment) | P49: M4250 datasheet DS-M4250-9Nov23 (fw 13.0.4) | Q49: All M4250 models
A50: PMB0312-10000S | B50: OnCall Cat 2 | C50: Support | D50: OnCall 24x7 1-year Cat 2 | N50: 12 | P50: M4250 datasheet DS-M4250-9Nov23 (fw 13.0.4)
A51: PMB0332-10000S | B51: OnCall Cat 2 | C51: Support | D51: OnCall 24x7 3-year Cat 2 | N51: 36 | P51: M4250 datasheet DS-M4250-9Nov23 (fw 13.0.4)
A52: PMB0352-10000S | B52: OnCall Cat 2 | C52: Support | D52: OnCall 24x7 5-year Cat 2 | N52: 60 | P52: M4250 datasheet DS-M4250-9Nov23 (fw 13.0.4)
A53: PMB0313-10000S | B53: OnCall Cat 3 | C53: Support | D53: OnCall 24x7 1-year Cat 3 | N53: 12 | P53: M4250 + M4350 datasheets
A54: PMB0333-10000S | B54: OnCall Cat 3 | C54: Support | D54: OnCall 24x7 3-year Cat 3 | N54: 36 | P54: M4250 + M4350 datasheets
A55: PMB0353-10000S | B55: OnCall Cat 3 | C55: Support | D55: OnCall 24x7 5-year Cat 3 | N55: 60 | P55: M4250 + M4350 datasheets
A56: PMB0314-10000S | B56: OnCall Cat 4 | C56: Support | D56: OnCall 24x7 1-year Cat 4 | N56: 12 | P56: M4350 datasheet DS-M4350-30May25 (fw 14.0) [file: M3450_Datasheet_30May25.pdf]
A57: PMB0334-10000S | B57: OnCall Cat 4 | C57: Support | D57: OnCall 24x7 3-year Cat 4 | N57: 36 | P57: M4350 datasheet DS-M4350-30May25 (fw 14.0) [file: M3450_Datasheet_30May25.pdf]
A58: PMB0354-10000S | B58: OnCall Cat 4 | C58: Support | D58: OnCall 24x7 5-year Cat 4 | N58: 60 | P58: M4350 datasheet DS-M4350-30May25 (fw 14.0) [file: M3450_Datasheet_30May25.pdf]
A59: SPR-WBE718-12 | B59: SPR-WBE718 | C59: Support | D59: Sprint 24/5 + advance RMA - 1 yr | N59: 12 | P59: WBE718 datasheet DS-WBE718_02Apr26
A60: SPR-WBE718-36 | B60: SPR-WBE718 | C60: Support | D60: Sprint 24/5 + advance RMA - 3 yr | N60: 36 | P60: WBE718 datasheet DS-WBE718_02Apr26
A61: SPR-WBE718-60 | B61: SPR-WBE718 | C61: Support | D61: Sprint 24/5 + advance RMA - 5 yr | N61: 60 | P61: WBE718 datasheet DS-WBE718_02Apr26
... A70: DRV-WBE758-60 | B70: DRV-WBE758 | C70: Support | D70: Overdrive/Drive 24/7 2h SLA + NBD RMA - 5 yr | N70: 60 | P70: WBE758 datasheet D-WBE758_29Jan24
A71: NGS25G-SR-OC | B71: NGS25G-SR-OC | C71: Optic | D71: 25GBASE-SR SFP28, multimode, 850 nm | E71: SFP28 | F71: 25 | G71: MMF | H71: LC duplex | I71: 100 | J71: OM3 70m; OM4 100m | O71: Limited lifetime (optic.ca) | P71: NETGEAR KB 000066694 (optic.ca, updated 2025-09-23) | Q71: Third-party: optic.ca, NETGEAR certified. Order from optic.ca
A72: NGS25G-LR-OC | B72: NGS25G-LR-OC | C72: Optic | D72: 25GBASE-LR SFP28, single mode, 1310 nm | E72: SFP28 | F72: 25 | G72: SMF | H72: LC duplex | I72: 10000 | J72: G.652 SMF | O72: Limited lifetime (optic.ca) | P72: NETGEAR KB 000066694 (optic.ca, updated 2025-09-23) | Q72: Third-party: optic.ca, NETGEAR certified. Order from optic.ca
A73: NGQ100G-SR4-OC | B73: NGQ100G-SR4-OC | C73: Optic | D73: 100GBASE-SR4 QSFP28, multimode, 850 nm | E73: QSFP28 | F73: 100 | G73: MMF | H73: MPO-12/UPC | I73: 100 | J73: OM3 70m; OM4 100m; 8-fiber parallel (MPO) | O73: Limited lifetime (optic.ca) | P73: NETGEAR KB 000066694 (optic.ca, updated 2025-09-23) | Q73: Third-party: optic.ca, NETGEAR certified. Order from optic.ca
A74: NGQ100G-LR4-OC | B74: NGQ100G-LR4-OC | C74: Optic | D74: 100GBASE-LR4 QSFP28, single mode, LWDM 1295-1309 nm | E74: QSFP28 | F74: 100 | G74: SMF | H74: LC duplex | I74: 10000 | J74: G.652 SMF | O74: Limited lifetime (optic.ca) | P74: NETGEAR KB 000066694 (optic.ca, updated 2025-09-23) | Q74: Third-party: optic.ca, NETGEAR certified. Order from optic.ca
A75: NGQ100G-PSM4-OC | B75: NGQ100G-PSM4-OC | C75: Optic | D75: 100GBASE-PSM4 QSFP28, single mode parallel, 1310 nm | E75: QSFP28 | F75: 100 | G75: SMF | H75: MPO-12/APC | I75: 500 | J75: G.652 SMF; 8-fiber parallel (MPO APC) | O75: Limited lifetime (optic.ca) | P75: NETGEAR KB 000066694 (optic.ca, updated 2025-09-23) | Q75: Third-party: optic.ca, NETGEAR certified. Order from optic.ca
A76: NGS25G-CU1M-OC | B76: NGS25G-CUxM-OC | C76: DAC | D76: 25G SFP28 DAC 1m, passive copper | E76: SFP28 | F76: 25 | G76: DAC passive | H76: SFP28 | I76: 1 | O76: Limited lifetime (optic.ca) | P76: NETGEAR KB 000066694 (optic.ca, updated 2025-09-23) | Q76: Third-party: optic.ca, NETGEAR certified. Order from optic.ca. Custom lengths to 5m on request
A77: NGS25G-CU2M-OC | B77: NGS25G-CUxM-OC | C77: DAC | D77: 25G SFP28 DAC 2m, passive copper | E77: SFP28 | F77: 25 | G77: DAC passive | H77: SFP28 | I77: 2 | O77: Limited lifetime (optic.ca) | P77: NETGEAR KB 000066694 (optic.ca, updated 2025-09-23) | Q77: Third-party: optic.ca, NETGEAR certified. Order from optic.ca. Custom lengths to 5m on request
A78: NGS25G-CU3M-OC | B78: NGS25G-CUxM-OC | C78: DAC | D78: 25G SFP28 DAC 3m, passive copper | E78: SFP28 | F78: 25 | G78: DAC passive | H78: SFP28 | I78: 3 | O78: Limited lifetime (optic.ca) | P78: NETGEAR KB 000066694 (optic.ca, updated 2025-09-23) | Q78: Third-party: optic.ca, NETGEAR certified. Order from optic.ca. Custom lengths to 5m on request
A79: NGS25G-CU5M-OC | B79: NGS25G-CUxM-OC | C79: DAC | D79: 25G SFP28 DAC 5m, passive copper | E79: SFP28 | F79: 25 | G79: DAC passive | H79: SFP28 | I79: 5 | O79: Limited lifetime (optic.ca) | P79: NETGEAR KB 000066694 (optic.ca, updated 2025-09-23) | Q79: Third-party: optic.ca, NETGEAR certified. Order from optic.ca. Custom lengths to 5m on request
A80: NGS25G-AO1M-OC | B80: NGS25G-AOxM-OC | C80: AOC | D80: 25G SFP28 1m, active optical cable | E80: SFP28 | F80: 25 | G80: AOC | H80: SFP28 | I80: 1 | O80: Limited lifetime (optic.ca) | P80: NETGEAR KB 000066694 (optic.ca, updated 2025-09-23) | Q80: Third-party: optic.ca, NETGEAR certified. Order from optic.ca. Custom lengths to 30m on request
A81: NGS25G-AO2M-OC | B81: NGS25G-AOxM-OC | C81: AOC | D81: 25G SFP28 2m, active optical cable | E81: SFP28 | F81: 25 | G81: AOC | H81: SFP28 | I81: 2 | O81: Limited lifetime (optic.ca) | P81: NETGEAR KB 000066694 (optic.ca, updated 2025-09-23) | Q81: Third-party: optic.ca, NETGEAR certified. Order from optic.ca. Custom lengths to 30m on request
A82: NGS25G-AO3M-OC | B82: NGS25G-AOxM-OC | C82: AOC | D82: 25G SFP28 3m, active optical cable | E82: SFP28 | F82: 25 | G82: AOC | H82: SFP28 | I82: 3 | O82: Limited lifetime (optic.ca) | P82: NETGEAR KB 000066694 (optic.ca, updated 2025-09-23) | Q82: Third-party: optic.ca, NETGEAR certified. Order from optic.ca. Custom lengths to 30m on request
A83: NGS25G-AO5M-OC | B83: NGS25G-AOxM-OC | C83: AOC | D83: 25G SFP28 5m, active optical cable | E83: SFP28 | F83: 25 | G83: AOC | H83: SFP28 | I83: 5 | O83: Limited lifetime (optic.ca) | P83: NETGEAR KB 000066694 (optic.ca, updated 2025-09-23) | Q83: Third-party: optic.ca, NETGEAR certified. Order from optic.ca. Custom lengths to 30m on request
A84: NGS25G-AO7M-OC | B84: NGS25G-AOxM-OC | C84: AOC | D84: 25G SFP28 7m, active optical cable | E84: SFP28 | F84: 25 | G84: AOC | H84: SFP28 | I84: 7 | O84: Limited lifetime (optic.ca) | P84: NETGEAR KB 000066694 (optic.ca, updated 2025-09-23) | Q84: Third-party: optic.ca, NETGEAR certified. Order from optic.ca. Custom lengths to 30m on request
A85: NGS25G-AO10M-OC | B85: NGS25G-AOxM-OC | C85: AOC | D85: 25G SFP28 10m, active optical cable | E85: SFP28 | F85: 25 | G85: AOC | H85: SFP28 | I85: 10 | O85: Limited lifetime (optic.ca) | P85: NETGEAR KB 000066694 (optic.ca, updated 2025-09-23) | Q85: Third-party: optic.ca, NETGEAR certified. Order from optic.ca. Custom lengths to 30m on request
A86: NGQ100G-CU1M-OC | B86: NGQ100G-CUxM-OC | C86: DAC | D86: 100G QSFP28 DAC 1m, passive copper | E86: QSFP28 | F86: 100 | G86: DAC passive | H86: QSFP28 | I86: 1 | O86: Limited lifetime (optic.ca) | P86: NETGEAR KB 000066694 (optic.ca, updated 2025-09-23) | Q86: Third-party: optic.ca, NETGEAR certified. Order from optic.ca. Custom lengths to 5m on request
A87: NGQ100G-CU2M-OC | B87: NGQ100G-CUxM-OC | C87: DAC | D87: 100G QSFP28 DAC 2m, passive copper | E87: QSFP28 | F87: 100 | G87: DAC passive | H87: QSFP28 | I87: 2 | O87: Limited lifetime (optic.ca) | P87: NETGEAR KB 000066694 (optic.ca, updated 2025-09-23) | Q87: Third-party: optic.ca, NETGEAR certified. Order from optic.ca. Custom lengths to 5m on request
... A105: NGQ4X25-AO10M-OC | B105: NGQ4X25-AOxM-OC | C105: Breakout Cable | D105: 100G QSFP28 to 4 x 25G SFP28 breakout 10m, active optical | E105: QSFP28 to 4x SFP28 | F105: 25 | G105: AOC | H105: QSFP28 / 4x SFP28 | I105: 10 | O105: Limited lifetime (optic.ca) | P105: NETGEAR KB 000066694 (optic.ca, updated 2025-09-23) | Q105: Third-party: optic.ca, NETGEAR certified. Order from optic.ca. Custom lengths to 30m on request. Breakout not used by engine yet

Sheet Compatibility
A1: Compatibility Map
A2: Scope_Type = Product (one Product_ID) or Family (applies to every product in that Family). Accessory_Base links to Accessories.Base_Model.
A4: Scope_Type | B4: Scope_Value | C4: Port_or_Slot | D4: Accessory_Base | E4: Relationship | F4: Max_Qty | G4: Constraint_Notes
A5: Family | B5: M4250 | C5: SFP (1G) | D5: AGM731F | E5: Optional optic | G5: 1G module
A6: Family | B6: M4250 | C6: SFP (1G) | D6: AGM732F | E6: Optional optic | G6: 1G module
A7: Family | B7: M4250 | C7: SFP (1G) | D7: AGM734 | E7: Optional optic | G7: 1G module
A8: Family | B8: M4250 | C8: SFP+ | D8: AGM731F | E8: Optional optic | G8: M4250-16XF: 1G modules on ports 1-12 only
A9: Family | B9: M4250 | C9: SFP+ | D9: AGM732F | E9: Optional optic | G9: M4250-16XF: 1G modules on ports 1-12 only
A10: Family | B10: M4250 | C10: SFP+ | D10: AGM734 | E10: Optional optic | G10: M4250-16XF: 1G modules on ports 1-12 only
A11: Family | B11: M4250 | C11: SFP+ | D11: AXM761 | E11: Optional optic/cable
A12: Family | B12: M4250 | C12: SFP+ | D12: AXM762 | E12: Optional optic/cable
A13: Family | B13: M4250 | C13: SFP+ | D13: AXM763 | E13: Optional optic/cable
A14: Family | B14: M4250 | C14: SFP+ | D14: AXM764 | E14: Optional optic/cable
A15: Family | B15: M4250 | C15: SFP+ | D15: AXM765 | E15: Optional optic/cable
A16: Family | B16: M4250 | C16: SFP+ | D16: AXC761 | E16: Optional optic/cable
A17: Family | B17: M4250 | C17: SFP+ | D17: AXC763 | E17: Optional optic/cable
A18: Family | B18: M4250 | C18: SFP+ | D18: AXC765 | E18: Optional optic/cable
A19: Family | B19: M4250 | C19: SFP+ | D19: AXC767 | E19: Optional optic/cable
A20: Family | B20: M4250 | C20: SFP+ | D20: AXC7610 | E20: Optional optic/cable
A21: Family | B21: M4250 | C21: SFP+ | D21: AXC7615 | E21: Optional optic/cable
A22: Family | B22: M4250 | C22: SFP+ | D22: AXC7620 | E22: Optional optic/cable
A23: Family | B23: M4350 | C23: SFP+ / SFP28 | D23: AGM731F | E23: Optional optic | G23: 1G module; on SFP28, whole 4-port block drops to 1G
A24: Family | B24: M4350 | C24: SFP+ / SFP28 | D24: AGM732F | E24: Optional optic | G24: 1G module; on SFP28, whole 4-port block drops to 1G
A25: Family | B25: M4350 | C25: SFP+ / SFP28 | D25: AGM734 | E25: Optional optic | G25: 1G module; on SFP28, whole 4-port block drops to 1G
A26: Family | B26: M4350 | C26: SFP+ / SFP28 | D26: AXM761 | E26: Optional optic/cable | G26: SFP28 at 10G: all 4 ports of the block must run 10G
A27: Family | B27: M4350 | C27: SFP+ / SFP28 | D27: AXM762 | E27: Optional optic/cable | G27: SFP28 at 10G: all 4 ports of the block must run 10G
A28: Family | B28: M4350 | C28: SFP+ / SFP28 | D28: AXM763 | E28: Optional optic/cable | G28: SFP28 at 10G: all 4 ports of the block must run 10G
A29: Family | B29: M4350 | C29: SFP+ / SFP28 | D29: AXM764 | E29: Optional optic/cable | G29: SFP28 at 10G: all 4 ports of the block must run 10G
A30: Family | B30: M4350 | C30: SFP+ / SFP28 | D30: AXM765 | E30: Optional optic/cable | G30: SFP28 at 10G: all 4 ports of the block must run 10G
A31: Family | B31: M4350 | C31: SFP+ / SFP28 | D31: AXC761 | E31: Optional optic/cable | G31: SFP28 at 10G: all 4 ports of the block must run 10G
A32: Family | B32: M4350 | C32: SFP+ / SFP28 | D32: AXC763 | E32: Optional optic/cable | G32: SFP28 at 10G: all 4 ports of the block must run 10G
A33: Family | B33: M4350 | C33: SFP+ / SFP28 | D33: AXC765 | E33: Optional optic/cable | G33: SFP28 at 10G: all 4 ports of the block must run 10G
A34: Family | B34: M4350 | C34: SFP+ / SFP28 | D34: AXC767 | E34: Optional optic/cable | G34: SFP28 at 10G: all 4 ports of the block must run 10G
... A38: Family | B38: M4350 | C38: SFP28 | D38: NGS25G-SR-OC | E38: Optional optic/cable | G38: 25G module: forces the whole 4-port SFP28 block to 25G (R01). Validated in KB 000066694
A39: Product | B39: GSM4328 | C39: PSU slot | D39: APS350W | E39: Optional PSU (RPS/EPS) | F39: 1 | G39: Do not mix PSU groups
A40: Product | B40: GSM4328 | C40: PSU slot | D40: APS600Wv2 | E40: Optional PSU (RPS/EPS) | F40: 1 | G40: Do not mix PSU groups
A41: Product | B41: GSM4328 | C41: PSU slot | D41: APS920W | E41: Optional PSU (RPS/EPS) | F41: 1 | G41: Do not mix PSU groups
A42: Product | B42: GSM4328 | C42: PSU slot | D42: APS2000W | E42: Optional PSU (RPS/EPS) | F42: 1 | G42: Do not mix PSU groups
A43: Product | B43: GSM4352 | C43: PSU slot | D43: APS350W | E43: Optional PSU (RPS/EPS) | F43: 2 | G43: Do not mix PSU groups
A44: Product | B44: GSM4352 | C44: PSU slot | D44: APS600Wv2 | E44: Optional PSU (RPS/EPS) | F44: 2 | G44: Do not mix PSU groups
A45: Product | B45: GSM4352 | C45: PSU slot | D45: APS920W | E45: Optional PSU (RPS/EPS) | F45: 2 | G45: Do not mix PSU groups
A46: Product | B46: GSM4352 | C46: PSU slot | D46: APS2000W | E46: Optional PSU (RPS/EPS) | F46: 2 | G46: Do not mix PSU groups
A47: Product | B47: MSM4310 | C47: PSU slot | D47: APS350W | E47: Optional PSU (RPS/EPS) | F47: 2 | G47: Do not mix PSU groups
A48: Product | B48: MSM4310 | C48: PSU slot | D48: APS600Wv2 | E48: Optional PSU (RPS/EPS) | F48: 2 | G48: Do not mix PSU groups
A49: Product | B49: MSM4310 | C49: PSU slot | D49: APS920W | E49: Optional PSU (RPS/EPS) | F49: 2 | G49: Do not mix PSU groups
A50: Product | B50: MSM4310 | C50: PSU slot | D50: APS2000W | E50: Optional PSU (RPS/EPS) | F50: 2 | G50: Do not mix PSU groups
... A86: Product | B86: XSM4344FC | C86: PSU slot | D86: APS2000Wv2 | E86: Optional PSU (RPS/EPS) | F86: 1 | G86: Do not mix PSU groups
A87: Product | B87: MSM4310 | C87: Mounting | D87: PST4310 | E87: Optional tray | G87: Half-width PSU tray, 2x APS254W
A88: Product | B88: GSM4210PX | C88: DC input | D88: APS254W | E88: Spare / replacement adapter | F88: 1 | G88: APS254W is the included adapter
A89: Product | B89: GSM4210PD | C89: Service | D89: OnCall Cat 2 | E89: Optional support | G89: PMB0312 / PMB0332 / PMB0352 (1/3/5 yr)
A90: Product | B90: GSM4210PX | C90: Service | D90: OnCall Cat 2 | E90: Optional support | G90: PMB0312 / PMB0332 / PMB0352 (1/3/5 yr)
A91: Product | B91: GSM4212P | C91: Service | D91: OnCall Cat 2 | E91: Optional support | G91: PMB0312 / PMB0332 / PMB0352 (1/3/5 yr)
A92: Product | B92: GSM4212PX | C92: Service | D92: OnCall Cat 2 | E92: Optional support | G92: PMB0312 / PMB0332 / PMB0352 (1/3/5 yr)
A93: Product | B93: GSM4212UX | C93: Service | D93: OnCall Cat 2 | E93: Optional support | G93: PMB0312 / PMB0332 / PMB0352 (1/3/5 yr)
A94: Product | B94: GSM4230P | C94: Service | D94: OnCall Cat 2 | E94: Optional support | G94: PMB0312 / PMB0332 / PMB0352 (1/3/5 yr)
A95: Product | B95: GSM4230UP | C95: Service | D95: OnCall Cat 3 | E95: Optional support | G95: PMB0313 / PMB0333 / PMB0353 (1/3/5 yr)
A96: Product | B96: GSM4230PX | C96: Service | D96: OnCall Cat 3 | E96: Optional support | G96: PMB0313 / PMB0333 / PMB0353 (1/3/5 yr)
A97: Product | B97: GSM4248P | C97: Service | D97: OnCall Cat 3 | E97: Optional support | G97: PMB0313 / PMB0333 / PMB0353 (1/3/5 yr)
A98: Product | B98: GSM4248PX | C98: Service | D98: OnCall Cat 3 | E98: Optional support | G98: PMB0313 / PMB0333 / PMB0353 (1/3/5 yr)
A99: Product | B99: GSM4248UX | C99: Service | D99: OnCall Cat 3 | E99: Optional support | G99: PMB0313 / PMB0333 / PMB0353 (1/3/5 yr)
A100: Product | B100: MSM4214X | C100: Service | D100: OnCall Cat 2 | E100: Optional support | G100: PMB0312 / PMB0332 / PMB0352 (1/3/5 yr)
... A133: Family | B133: M4350 | C133: QSFP28 (breakout) | D133: NGQ4X25-AOxM-OC | E133: Optional optic/cable | G133: QSFP28 port in 4x25G breakout mode; SFP28 ends force their blocks to 25G (R01). Validated in KB 000066694

Sheet PSU_PoE_Matrix
A1: PoE Budget by PSU Configuration (RPS + EPS)
A2: EPS = all PSUs powered. 'If internal fails' is from the datasheet matrix; 'If one module fails' = same config with one module fewer. Protected (grey) = worst case of the two = what to design to when redundancy is required. Blank = non-PoE model.
A4: Product_ID | B4: Model_Name | C4: Internal_PSU | D4: PSU_Module | E4: Module_Qty | F4: Input_Voltage | G4: PoE_Budget_EPS_W | H4: PoE_If_Internal_PSU_Fails_W | I4: PoE_If_One_Module_Fails_W | J4: PoE_Budget_Protected_W | K4: Config_Label | L4: Notes
A5: GSM4328 | B5: M4350-24G4XF | C5: 880W internal | D5: None | E5: 0 | F5: 110-240 VAC | G5: 648 | J5: =IF(COUNT(H5,I5)=0,"",MIN(H5,I5)) | K5: Base (no module) | L5: Base budget, no redundancy
A6: GSM4328 | B6: M4350-24G4XF | C6: 880W internal | D6: APS350W | E6: 1 | F6: 110-240 VAC | G6: 720 | H6: 218 | I6: 648 | J6: =IF(COUNT(H6,I6)=0,"",MIN(H6,I6)) | K6: 1x APS350W
A7: GSM4328 | B7: M4350-24G4XF | C7: 880W internal | D7: APS600Wv2 | E7: 1 | F7: 110-240 VAC | G7: 720 | H7: 468 | I7: 648 | J7: =IF(COUNT(H7,I7)=0,"",MIN(H7,I7)) | K7: 1x APS600Wv2
A8: GSM4328 | B8: M4350-24G4XF | C8: 880W internal | D8: APS920W | E8: 1 | F8: 110-240 VAC | G8: 720 | H8: 720 | I8: 648 | J8: =IF(COUNT(H8,I8)=0,"",MIN(H8,I8)) | K8: 1x APS920W
A9: GSM4328 | B9: M4350-24G4XF | C9: 880W internal | D9: APS2000W | E9: 1 | F9: 110 VAC | G9: 720 | H9: 720 | I9: 648 | J9: =IF(COUNT(H9,I9)=0,"",MIN(H9,I9)) | K9: 1x APS2000W @110V
A10: GSM4328 | B10: M4350-24G4XF | C10: 880W internal | D10: APS2000W | E10: 1 | F10: 220 VAC | G10: 720 | H10: 720 | I10: 648 | J10: =IF(COUNT(H10,I10)=0,"",MIN(H10,I10)) | K10: 1x APS2000W @220V
A11: GSM4352 | B11: M4350-48G4XF | C11: 550W internal | D11: None | E11: 0 | F11: 110-240 VAC | G11: 236 | J11: =IF(COUNT(H11,I11)=0,"",MIN(H11,I11)) | K11: Base (no module) | L11: Base budget, no redundancy
A12: GSM4352 | B12: M4350-48G4XF | C12: 550W internal | D12: APS350W | E12: 1 | F12: 110-240 VAC | G12: 436 | H12: 186 | I12: 236 | J12: =IF(COUNT(H12,I12)=0,"",MIN(H12,I12)) | K12: 1x APS350W
A13: GSM4352 | B13: M4350-48G4XF | C13: 550W internal | D13: APS600Wv2 | E13: 1 | F13: 110-240 VAC | G13: 636 | H13: 436 | I13: 236 | J13: =IF(COUNT(H13,I13)=0,"",MIN(H13,I13)) | K13: 1x APS600Wv2
A14: GSM4352 | B14: M4350-48G4XF | C14: 550W internal | D14: APS920W | E14: 1 | F14: 110-240 VAC | G14: 892 | H14: 756 | I14: 236 | J14: =IF(COUNT(H14,I14)=0,"",MIN(H14,I14)) | K14: 1x APS920W
A15: GSM4352 | B15: M4350-48G4XF | C15: 550W internal | D15: APS2000W | E15: 1 | F15: 110 VAC | G15: 956 | H15: 836 | I15: 236 | J15: =IF(COUNT(H15,I15)=0,"",MIN(H15,I15)) | K15: 1x APS2000W @110V
A16: GSM4352 | B16: M4350-48G4XF | C16: 550W internal | D16: APS2000W | E16: 1 | F16: 220 VAC | G16: 1440 | H16: 1440 | I16: 236 | J16: =IF(COUNT(H16,I16)=0,"",MIN(H16,I16)) | K16: 1x APS2000W @220V
A17: GSM4352 | B17: M4350-48G4XF | C17: 550W internal | D17: APS350W | E17: 2 | F17: 110-240 VAC | G17: 716 | H17: 396 | I17: 436 | J17: =IF(COUNT(H17,I17)=0,"",MIN(H17,I17)) | K17: 2x APS350W
A18: GSM4352 | B18: M4350-48G4XF | C18: 550W internal | D18: APS600Wv2 | E18: 2 | F18: 110-240 VAC | G18: 1116 | H18: 796 | I18: 636 | J18: =IF(COUNT(H18,I18)=0,"",MIN(H18,I18)) | K18: 2x APS600Wv2
A19: GSM4352 | B19: M4350-48G4XF | C19: 550W internal | D19: APS920W | E19: 2 | F19: 110-240 VAC | G19: 1440 | H19: 1308 | I19: 892 | J19: =IF(COUNT(H19,I19)=0,"",MIN(H19,I19)) | K19: 2x APS920W
A20: GSM4352 | B20: M4350-48G4XF | C20: 550W internal | D20: APS2000W | E20: 2 | F20: 110 VAC | G20: 1440 | H20: 1436 | I20: 956 | J20: =IF(COUNT(H20,I20)=0,"",MIN(H20,I20)) | K20: 2x APS2000W @110V
A21: GSM4352 | B21: M4350-48G4XF | C21: 550W internal | D21: APS2000W | E21: 2 | F21: 220 VAC | G21: 1440 | H21: 1440 | I21: 1440 | J21: =IF(COUNT(H21,I21)=0,"",MIN(H21,I21)) | K21: 2x APS2000W @220V
A22: MSM4310 | B22: M4350-8M2V | C22: APS254W (included) | D22: None | E22: 0 | F22: 110-240 VAC | G22: 119 | J22: =IF(COUNT(H22,I22)=0,"",MIN(H22,I22)) | K22: Base (no module) | L22: Base budget, no redundancy
A23: MSM4310 | B23: M4350-8M2V | C23: APS254W (included) | D23: APS254W | E23: 1 | F23: 110-240 VAC | G23: 322 | H23: 119 | I23: 119 | J23: =IF(COUNT(H23,I23)=0,"",MIN(H23,I23)) | K23: 1x APS254W
A24: MSM4310 | B24: M4350-8M2V | C24: APS254W (included) | D24: APS254W | E24: 2 | F24: 110-240 VAC | G24: 551 | H24: 322 | I24: 322 | J24: =IF(COUNT(H24,I24)=0,"",MIN(H24,I24)) | K24: 2x APS254W
A25: MSM4332 | B25: M4350-24M4X4V | C25: 800W internal | D25: None | E25: 0 | F25: 110-240 VAC | G25: 522 | J25: =IF(COUNT(H25,I25)=0,"",MIN(H25,I25)) | K25: Base (no module) | L25: Base budget, no redundancy
A26: MSM4332 | B26: M4350-24M4X4V | C26: 800W internal | D26: APS600Wv3 | E26: 1 | F26: 110-240 VAC | G26: 852 | H26: 372 | I26: 522 | J26: =IF(COUNT(H26,I26)=0,"",MIN(H26,I26)) | K26: 1x APS600Wv3
A27: MSM4332 | B27: M4350-24M4X4V | C27: 800W internal | D27: APS1200Wv2 | E27: 1 | F27: 110 VAC | G27: 1172 | H27: 772 | I27: 522 | J27: =IF(COUNT(H27,I27)=0,"",MIN(H27,I27)) | K27: 1x APS1200Wv2 @110V
A28: MSM4332 | B28: M4350-24M4X4V | C28: 800W internal | D28: APS1200Wv2 | E28: 1 | F28: 220 VAC | G28: 1332 | H28: 972 | I28: 522 | J28: =IF(COUNT(H28,I28)=0,"",MIN(H28,I28)) | K28: 1x APS1200Wv2 @220V
A29: MSM4332 | B29: M4350-24M4X4V | C29: 800W internal | D29: APS2000Wv2 | E29: 1 | F29: 110 VAC | G29: 1172 | H29: 772 | I29: 522 | J29: =IF(COUNT(H29,I29)=0,"",MIN(H29,I29)) | K29: 1x APS2000Wv2 @110V
A30: MSM4332 | B30: M4350-24M4X4V | C30: 800W internal | D30: APS2000Wv2 | E30: 1 | F30: 220 VAC | G30: 1972 | H30: 1772 | I30: 522 | J30: =IF(COUNT(H30,I30)=0,"",MIN(H30,I30)) | K30: 1x APS2000Wv2 @220V
A31: MSM4332 | B31: M4350-24M4X4V | C31: 800W internal | D31: APS600Wv3 | E31: 2 | F31: 110-240 VAC | G31: 1332 | H31: 732 | I31: 852 | J31: =IF(COUNT(H31,I31)=0,"",MIN(H31,I31)) | K31: 2x APS600Wv3
A32: MSM4332 | B32: M4350-24M4X4V | C32: 800W internal | D32: APS1200Wv2 | E32: 2 | F32: 110 VAC | G32: 1972 | H32: 1372 | I32: 1172 | J32: =IF(COUNT(H32,I32)=0,"",MIN(H32,I32)) | K32: 2x APS1200Wv2 @110V
A33: MSM4332 | B33: M4350-24M4X4V | C33: 800W internal | D33: APS1200Wv2 | E33: 2 | F33: 220 VAC | G33: 2292 | H33: 1692 | I33: 1332 | J33: =IF(COUNT(H33,I33)=0,"",MIN(H33,I33)) | K33: 2x APS1200Wv2 @220V
A34: MSM4332 | B34: M4350-24M4X4V | C34: 800W internal | D34: APS2000Wv2 | E34: 2 | F34: 110 VAC | G34: 1972 | H34: 1372 | I34: 1172 | J34: =IF(COUNT(H34,I34)=0,"",MIN(H34,I34)) | K34: 2x APS2000Wv2 @110V
A35: MSM4332 | B35: M4350-24M4X4V | C35: 800W internal | D35: APS2000Wv2 | E35: 2 | F35: 220 VAC | G35: 2520 | H35: 2520 | I35: 1972 | J35: =IF(COUNT(H35,I35)=0,"",MIN(H35,I35)) | K35: 2x APS2000Wv2 @220V
A36: MSM4352 | B36: M4350-44M4X4V | C36: 550W internal | D36: None | E36: 0 | F36: 110-240 VAC | G36: 194 | J36: =IF(COUNT(H36,I36)=0,"",MIN(H36,I36)) | K36: Base (no module) | L36: Base budget, no redundancy
A37: MSM4352 | B37: M4350-44M4X4V | C37: 550W internal | D37: APS350W | E37: 1 | F37: 110-240 VAC | G37: 394 | H37: 144 | I37: 194 | J37: =IF(COUNT(H37,I37)=0,"",MIN(H37,I37)) | K37: 1x APS350W
A38: MSM4352 | B38: M4350-44M4X4V | C38: 550W internal | D38: APS600Wv2 | E38: 1 | F38: 110-240 VAC | G38: 594 | H38: 394 | I38: 194 | J38: =IF(COUNT(H38,I38)=0,"",MIN(H38,I38)) | K38: 1x APS600Wv2
A39: MSM4352 | B39: M4350-44M4X4V | C39: 550W internal | D39: APS920W | E39: 1 | F39: 110-240 VAC | G39: 850 | H39: 714 | I39: 194 | J39: =IF(COUNT(H39,I39)=0,"",MIN(H39,I39)) | K39: 1x APS920W
A40: MSM4352 | B40: M4350-44M4X4V | C40: 550W internal | D40: APS2000W | E40: 1 | F40: 110 VAC | G40: 914 | H40: 794 | I40: 194 | J40: =IF(COUNT(H40,I40)=0,"",MIN(H40,I40)) | K40: 1x APS2000W @110V
A41: MSM4352 | B41: M4350-44M4X4V | C41: 550W internal | D41: APS2000W | E41: 1 | F41: 220 VAC | G41: 1786 | H41: 1694 | I41: 194 | J41: =IF(COUNT(H41,I41)=0,"",MIN(H41,I41)) | K41: 1x APS2000W @220V
A42: MSM4352 | B42: M4350-44M4X4V | C42: 550W internal | D42: APS350W | E42: 2 | F42: 110-240 VAC | G42: 674 | H42: 354 | I42: 394 | J42: =IF(COUNT(H42,I42)=0,"",MIN(H42,I42)) | K42: 2x APS350W
A43: MSM4352 | B43: M4350-44M4X4V | C43: 550W internal | D43: APS600Wv2 | E43: 2 | F43: 110-240 VAC | G43: 1074 | H43: 754 | I43: 594 | J43: =IF(COUNT(H43,I43)=0,"",MIN(H43,I43)) | K43: 2x APS600Wv2
A44: MSM4352 | B44: M4350-44M4X4V | C44: 550W internal | D44: APS920W | E44: 2 | F44: 110-240 VAC | G44: 1586 | H44: 1266 | I44: 850 | J44: =IF(COUNT(H44,I44)=0,"",MIN(H44,I44)) | K44: 2x APS920W
A45: MSM4352 | B45: M4350-44M4X4V | C45: 550W internal | D45: APS2000W | E45: 2 | F45: 110 VAC | G45: 1714 | H45: 1394 | I45: 914 | J45: =IF(COUNT(H45,I45)=0,"",MIN(H45,I45)) | K45: 2x APS2000W @110V
A46: MSM4352 | B46: M4350-44M4X4V | C46: 550W internal | D46: APS2000W | E46: 2 | F46: 220 VAC | G46: 3314 | H46: 2994 | I46: 1786 | J46: =IF(COUNT(H46,I46)=0,"",MIN(H46,I46)) | K46: 2x APS2000W @220V
A47: MSM4328F | B47: M4350-24F4X | C47: 240W internal | D47: None | E47: 0 | F47: 110-240 VAC | J47: =IF(COUNT(H47,I47)=0,"",MIN(H47,I47)) | K47: Base (no module) | L47: Base budget, no redundancy
A48: MSM4328F | B48: M4350-24F4X | C48: 240W internal | D48: APS600Wv3 | E48: 1 | F48: 110-240 VAC | J48: =IF(COUNT(H48,I48)=0,"",MIN(H48,I48)) | K48: 1x APS600Wv3
A49: MSM4328F | B49: M4350-24F4X | C49: 240W internal | D49: APS1200Wv2 | E49: 1 | F49: 110 VAC | J49: =IF(COUNT(H49,I49)=0,"",MIN(H49,I49)) | K49: 1x APS1200Wv2 @110V
A50: MSM4328F | B50: M4350-24F4X | C50: 240W internal | D50: APS1200Wv2 | E50: 1 | F50: 220 VAC | J50: =IF(COUNT(H50,I50)=0,"",MIN(H50,I50)) | K50: 1x APS1200Wv2 @220V
A51: MSM4328F | B51: M4350-24F4X | C51: 240W internal | D51: APS2000Wv2 | E51: 1 | F51: 110 VAC | J51: =IF(COUNT(H51,I51)=0,"",MIN(H51,I51)) | K51: 1x APS2000Wv2 @110V
A52: MSM4328F | B52: M4350-24F4X | C52: 240W internal | D52: APS2000Wv2 | E52: 1 | F52: 220 VAC | J52: =IF(COUNT(H52,I52)=0,"",MIN(H52,I52)) | K52: 1x APS2000Wv2 @220V
A53: XSM4328CV | B53: M4350-24X4V | C53: 880W internal | D53: None | E53: 0 | F53: 110-240 VAC | G53: 576 | J53: =IF(COUNT(H53,I53)=0,"",MIN(H53,I53)) | K53: Base (no module) | L53: Base budget, no redundancy
A54: XSM4328CV | B54: M4350-24X4V | C54: 880W internal | D54: APS350W | E54: 1 | F54: 110-240 VAC | G54: 700 | H54: 146 | I54: 576 | J54: =IF(COUNT(H54,I54)=0,"",MIN(H54,I54)) | K54: 1x APS350W
A55: XSM4328CV | B55: M4350-24X4V | C55: 880W internal | D55: APS600Wv2 | E55: 1 | F55: 110-240 VAC | G55: 720 | H55: 396 | I55: 576 | J55: =IF(COUNT(H55,I55)=0,"",MIN(H55,I55)) | K55: 1x APS600Wv2
A56: XSM4328CV | B56: M4350-24X4V | C56: 880W internal | D56: APS920W | E56: 1 | F56: 110-240 VAC | G56: 720 | H56: 716 | I56: 576 | J56: =IF(COUNT(H56,I56)=0,"",MIN(H56,I56)) | K56: 1x APS920W
A57: XSM4328CV | B57: M4350-24X4V | C57: 880W internal | D57: APS2000W | E57: 1 | F57: 110 VAC | G57: 720 | H57: 720 | I57: 576 | J57: =IF(COUNT(H57,I57)=0,"",MIN(H57,I57)) | K57: 1x APS2000W @110V
A58: XSM4328CV | B58: M4350-24X4V | C58: 880W internal | D58: APS2000W | E58: 1 | F58: 220 VAC | G58: 720 | H58: 720 | I58: 576 | J58: =IF(COUNT(H58,I58)=0,"",MIN(H58,I58)) | K58: 1x APS2000W @220V
A59: XSM4328FV | B59: M4350-24F4V | C59: 240W internal | D59: None | E59: 0 | F59: 110-240 VAC | J59: =IF(COUNT(H59,I59)=0,"",MIN(H59,I59)) | K59: Base (no module) | L59: Base budget, no redundancy
A60: XSM4328FV | B60: M4350-24F4V | C60: 240W internal | D60: APS350W | E60: 1 | F60: 110-240 VAC | J60: =IF(COUNT(H60,I60)=0,"",MIN(H60,I60)) | K60: 1x APS350W
A61: XSM4328FV | B61: M4350-24F4V | C61: 240W internal | D61: APS600Wv2 | E61: 1 | F61: 110-240 VAC | J61: =IF(COUNT(H61,I61)=0,"",MIN(H61,I61)) | K61: 1x APS600Wv2
A62: XSM4328FV | B62: M4350-24F4V | C62: 240W internal | D62: APS920W | E62: 1 | F62: 110-240 VAC | J62: =IF(COUNT(H62,I62)=0,"",MIN(H62,I62)) | K62: 1x APS920W
A63: XSM4328FV | B63: M4350-24F4V | C63: 240W internal | D63: APS2000W | E63: 1 | F63: 110 VAC | J63: =IF(COUNT(H63,I63)=0,"",MIN(H63,I63)) | K63: 1x APS2000W @110V
A64: XSM4328FV | B64: M4350-24F4V | C64: 240W internal | D64: APS2000W | E64: 1 | F64: 220 VAC | J64: =IF(COUNT(H64,I64)=0,"",MIN(H64,I64)) | K64: 1x APS2000W @220V
A65: XSM4340CV | B65: M4350-36X4V | C65: 750W internal | D65: None | E65: 0 | F65: 110-240 VAC | G65: 280 | J65: =IF(COUNT(H65,I65)=0,"",MIN(H65,I65)) | K65: Base (no module) | L65: Base budget, no redundancy
A66: XSM4340CV | B66: M4350-36X4V | C66: 750W internal | D66: APS600Wv3 | E66: 1 | F66: 110-240 VAC | G66: 640 | H66: 280 | I66: 280 | J66: =IF(COUNT(H66,I66)=0,"",MIN(H66,I66)) | K66: 1x APS600Wv3
A67: XSM4340CV | B67: M4350-36X4V | C67: 750W internal | D67: APS1200Wv2 | E67: 1 | F67: 110 VAC | G67: 960 | H67: 680 | I67: 280 | J67: =IF(COUNT(H67,I67)=0,"",MIN(H67,I67)) | K67: 1x APS1200Wv2 @110V
A68: XSM4340CV | B68: M4350-36X4V | C68: 750W internal | D68: APS1200Wv2 | E68: 1 | F68: 220 VAC | G68: 1120 | H68: 880 | I68: 280 | J68: =IF(COUNT(H68,I68)=0,"",MIN(H68,I68)) | K68: 1x APS1200Wv2 @220V
A69: XSM4340CV | B69: M4350-36X4V | C69: 750W internal | D69: APS2000Wv2 | E69: 1 | F69: 110 VAC | G69: 960 | H69: 680 | I69: 280 | J69: =IF(COUNT(H69,I69)=0,"",MIN(H69,I69)) | K69: 1x APS2000Wv2 @110V
A70: XSM4340CV | B70: M4350-36X4V | C70: 750W internal | D70: APS2000Wv2 | E70: 1 | F70: 220 VAC | G70: 1760 | H70: 1680 | I70: 280 | J70: =IF(COUNT(H70,I70)=0,"",MIN(H70,I70)) | K70: 1x APS2000Wv2 @220V
A71: XSM4340V | B71: M4350-24X8F8V | C71: 750W internal | D71: None | E71: 0 | F71: 110-240 VAC | G71: 290 | J71: =IF(COUNT(H71,I71)=0,"",MIN(H71,I71)) | K71: Base (no module) | L71: Base budget, no redundancy
A72: XSM4340V | B72: M4350-24X8F8V | C72: 750W internal | D72: APS600Wv3 | E72: 1 | F72: 110-240 VAC | G72: 650 | H72: 290 | I72: 290 | J72: =IF(COUNT(H72,I72)=0,"",MIN(H72,I72)) | K72: 1x APS600Wv3
A73: XSM4340V | B73: M4350-24X8F8V | C73: 750W internal | D73: APS1200Wv2 | E73: 1 | F73: 110 VAC | G73: 970 | H73: 690 | I73: 290 | J73: =IF(COUNT(H73,I73)=0,"",MIN(H73,I73)) | K73: 1x APS1200Wv2 @110V
A74: XSM4340V | B74: M4350-24X8F8V | C74: 750W internal | D74: APS1200Wv2 | E74: 1 | F74: 220 VAC | G74: 1130 | H74: 890 | I74: 290 | J74: =IF(COUNT(H74,I74)=0,"",MIN(H74,I74)) | K74: 1x APS1200Wv2 @220V
A75: XSM4340V | B75: M4350-24X8F8V | C75: 750W internal | D75: APS2000Wv2 | E75: 1 | F75: 110 VAC | G75: 970 | H75: 690 | I75: 290 | J75: =IF(COUNT(H75,I75)=0,"",MIN(H75,I75)) | K75: 1x APS2000Wv2 @110V
A76: XSM4340V | B76: M4350-24X8F8V | C76: 750W internal | D76: APS2000Wv2 | E76: 1 | F76: 220 VAC | G76: 1770 | H76: 1690 | I76: 290 | J76: =IF(COUNT(H76,I76)=0,"",MIN(H76,I76)) | K76: 1x APS2000Wv2 @220V
A77: XSM4340FV | B77: M4350-32F8V | C77: 420W internal | D77: None | E77: 0 | F77: 110-240 VAC | J77: =IF(COUNT(H77,I77)=0,"",MIN(H77,I77)) | K77: Base (no module) | L77: Base budget, no redundancy
A78: XSM4340FV | B78: M4350-32F8V | C78: 420W internal | D78: APS600Wv3 | E78: 1 | F78: 110-240 VAC | J78: =IF(COUNT(H78,I78)=0,"",MIN(H78,I78)) | K78: 1x APS600Wv3
A79: XSM4340FV | B79: M4350-32F8V | C79: 420W internal | D79: APS1200Wv2 | E79: 1 | F79: 110 VAC | J79: =IF(COUNT(H79,I79)=0,"",MIN(H79,I79)) | K79: 1x APS1200Wv2 @110V
A80: XSM4340FV | B80: M4350-32F8V | C80: 420W internal | D80: APS1200Wv2 | E80: 1 | F80: 220 VAC | J80: =IF(COUNT(H80,I80)=0,"",MIN(H80,I80)) | K80: 1x APS1200Wv2 @220V
A81: XSM4340FV | B81: M4350-32F8V | C81: 420W internal | D81: APS2000Wv2 | E81: 1 | F81: 110 VAC | J81: =IF(COUNT(H81,I81)=0,"",MIN(H81,I81)) | K81: 1x APS2000Wv2 @110V
A82: XSM4340FV | B82: M4350-32F8V | C82: 420W internal | D82: APS2000Wv2 | E82: 1 | F82: 220 VAC | J82: =IF(COUNT(H82,I82)=0,"",MIN(H82,I82)) | K82: 1x APS2000Wv2 @220V
A83: VSM4320C | B83: M4350-16V4C | C83: 420W internal | D83: None | E83: 0 | F83: 110-240 VAC | J83: =IF(COUNT(H83,I83)=0,"",MIN(H83,I83)) | K83: Base (no module) | L83: Base budget, no redundancy
A84: VSM4320C | B84: M4350-16V4C | C84: 420W internal | D84: APS600Wv3 | E84: 1 | F84: 110-240 VAC | J84: =IF(COUNT(H84,I84)=0,"",MIN(H84,I84)) | K84: 1x APS600Wv3
A85: VSM4320C | B85: M4350-16V4C | C85: 420W internal | D85: APS1200Wv2 | E85: 1 | F85: 110 VAC | J85: =IF(COUNT(H85,I85)=0,"",MIN(H85,I85)) | K85: 1x APS1200Wv2 @110V
A86: VSM4320C | B86: M4350-16V4C | C86: 420W internal | D86: APS1200Wv2 | E86: 1 | F86: 220 VAC | J86: =IF(COUNT(H86,I86)=0,"",MIN(H86,I86)) | K86: 1x APS1200Wv2 @220V
A87: VSM4320C | B87: M4350-16V4C | C87: 420W internal | D87: APS2000Wv2 | E87: 1 | F87: 110 VAC | J87: =IF(COUNT(H87,I87)=0,"",MIN(H87,I87)) | K87: 1x APS2000Wv2 @110V
A88: VSM4320C | B88: M4350-16V4C | C88: 420W internal | D88: APS2000Wv2 | E88: 1 | F88: 220 VAC | J88: =IF(COUNT(H88,I88)=0,"",MIN(H88,I88)) | K88: 1x APS2000Wv2 @220V
A89: XSM4344C | B89: M4350-40X4C | C89: 750W internal | D89: None | E89: 0 | F89: 110-240 VAC | G89: 196 | J89: =IF(COUNT(H89,I89)=0,"",MIN(H89,I89)) | K89: Base (no module) | L89: Base budget, no redundancy
A90: XSM4344C | B90: M4350-40X4C | C90: 750W internal | D90: APS600Wv3 | E90: 1 | F90: 110-240 VAC | G90: 556 | H90: 196 | I90: 196 | J90: =IF(COUNT(H90,I90)=0,"",MIN(H90,I90)) | K90: 1x APS600Wv3
A91: XSM4344C | B91: M4350-40X4C | C91: 750W internal | D91: APS1200Wv2 | E91: 1 | F91: 110 VAC | G91: 876 | H91: 596 | I91: 196 | J91: =IF(COUNT(H91,I91)=0,"",MIN(H91,I91)) | K91: 1x APS1200Wv2 @110V
A92: XSM4344C | B92: M4350-40X4C | C92: 750W internal | D92: APS1200Wv2 | E92: 1 | F92: 220 VAC | G92: 1036 | H92: 796 | I92: 196 | J92: =IF(COUNT(H92,I92)=0,"",MIN(H92,I92)) | K92: 1x APS1200Wv2 @220V
A93: XSM4344C | B93: M4350-40X4C | C93: 750W internal | D93: APS2000Wv2 | E93: 1 | F93: 110 VAC | G93: 876 | H93: 596 | I93: 196 | J93: =IF(COUNT(H93,I93)=0,"",MIN(H93,I93)) | K93: 1x APS2000Wv2 @110V
A94: XSM4344C | B94: M4350-40X4C | C94: 750W internal | D94: APS2000Wv2 | E94: 1 | F94: 220 VAC | G94: 1676 | H94: 1596 | I94: 196 | J94: =IF(COUNT(H94,I94)=0,"",MIN(H94,I94)) | K94: 1x APS2000Wv2 @220V
A95: XSM4344FC | B95: M4350-40F4C | C95: 420W internal | D95: None | E95: 0 | F95: 110-240 VAC | J95: =IF(COUNT(H95,I95)=0,"",MIN(H95,I95)) | K95: Base (no module) | L95: Base budget, no redundancy
A96: XSM4344FC | B96: M4350-40F4C | C96: 420W internal | D96: APS600Wv3 | E96: 1 | F96: 110-240 VAC | J96: =IF(COUNT(H96,I96)=0,"",MIN(H96,I96)) | K96: 1x APS600Wv3
A97: XSM4344FC | B97: M4350-40F4C | C97: 420W internal | D97: APS1200Wv2 | E97: 1 | F97: 110 VAC | J97: =IF(COUNT(H97,I97)=0,"",MIN(H97,I97)) | K97: 1x APS1200Wv2 @110V
A98: XSM4344FC | B98: M4350-40F4C | C98: 420W internal | D98: APS1200Wv2 | E98: 1 | F98: 220 VAC | J98: =IF(COUNT(H98,I98)=0,"",MIN(H98,I98)) | K98: 1x APS1200Wv2 @220V
A99: XSM4344FC | B99: M4350-40F4C | C99: 420W internal | D99: APS2000Wv2 | E99: 1 | F99: 110 VAC | J99: =IF(COUNT(H99,I99)=0,"",MIN(H99,I99)) | K99: 1x APS2000Wv2 @110V
A100: XSM4344FC | B100: M4350-40F4C | C100: 420W internal | D100: APS2000Wv2 | E100: 1 | F100: 220 VAC | J100: =IF(COUNT(H100,I100)=0,"",MIN(H100,I100)) | K100: 1x APS2000Wv2 @220V
A101: GSM4230UP | B101: M4250-26G4F-PoE++ | C101: 2x internal | D101: (internal PSUs) | E101: 1 | F101: 110 VAC | G101: 720 | J101: =IF(COUNT(H101,I101)=0,"",MIN(H101,I101)) | K101: 1 of 2 PSUs powered | L101: No redundancy
...

Sheet Design_Rules
A1: Design Rules & Constraints for the BoM Engine
A2: Encode these as validation logic in the tool. Add a row whenever a datasheet footnote changes what can be ordered.
A4: Rule_ID | B4: Applies_To | C4: Area | D4: Rule | E4: BoM_Impact | F4: Source
A5: R01 | B5: M4350 (all) | C5: Ports | D5: Each 4x25G SFP28 block runs at one speed (4x1G / 4x10G / 4x25G). A single 25G optic forces the block to 25G and drops 10G/1G optics in that block. | E5: Group uplink optics per 4-port block; never mix 25G and 10G in one block. | F5: M4350 datasheet DS-M4350-30May25 (fw 14.0) [file: M3450_Datasheet_30May25.pdf]
A6: R02 | B6: M4350 (all) | C6: Stacking | D6: Stack links run only at the port's highest speed (25G on SFP28, 100G on QSFP28). Up to 8 units, NSF/hitless failover. | E6: Stack cables/optics must be 25G or 100G. | F6: M4350 datasheet DS-M4350-30May25 (fw 14.0) [file: M3450_Datasheet_30May25.pdf]
A7: R03 | B7: M4350 (all) | C7: Features | D7: Stacking, AVB and PTP TC/BC/GM are mutually exclusive. | E7: If AVB or PTP (ST 2110/AES67 BC) is required, do not propose a stack; use LAG/MLAG-style design. | F7: M4350 datasheet DS-M4350-30May25 (fw 14.0) [file: M3450_Datasheet_30May25.pdf]
A8: R04 | B8: M4250 (all) | C8: Features | D8: AVB is not supported on a LAG. Max 256 AVB streams per switch. | E8: AVB designs need single uplinks or MSTP, not LAG. | F8: M4250 datasheet DS-M4250-9Nov23 (fw 13.0.4)
A9: R05 | B9: M4350 full width | C9: Power | D9: RPS+EPS work simultaneously: total budget (EPS) and protected budget (internal PSU failed) depend on PSU model, quantity and input voltage. | E9: When redundancy is required, size PoE to PoE_Budget_Protected_W (worst of internal-PSU or module failure), not the EPS total. | F9: M4350 datasheet DS-M4350-30May25 (fw 14.0) [file: M3450_Datasheet_30May25.pdf]
A10: R06 | B10: M4350 | C10: Power | D10: Two PSU groups: A (APS350W/600Wv2/920W/2000W) and B (APS600Wv3/1200Wv2/2000Wv2) are model-specific. | E10: Only offer PSUs listed in Compatibility for the chosen model. | F10: M4350 datasheet DS-M4350-30May25 (fw 14.0) [file: M3450_Datasheet_30May25.pdf]
A11: R07 | B11: APS2000W / APS2000Wv2 | C11: Power | D11: Output is 1,000W at 110VAC and 2,000W at 220VAC. | E11: Ask for site input voltage before sizing high PoE budgets. | F11: M4350 datasheet DS-M4350-30May25 (fw 14.0) [file: M3450_Datasheet_30May25.pdf]
A12: R08 | B12: M4250-26G4F-PoE++ / 40G8XF-PoE++ | C12: Power | D12: PoE budget scales with number of powered internal PSUs (720 / 1,440W; 720 / 1,650 / 2,880W). | E12: Budget = f(PSUs powered). Redundancy reduces usable budget. | F12: M4250 datasheet DS-M4250-9Nov23 (fw 13.0.4)
A13: R09 | B13: M4250 / M4350 | C13: PoE | D13: PoE+ ports: max 30W/port; Ultra90 PoE++ ports: 15.4/30/60/75/90W classes. | E13: Match endpoint class to port type; 60-90W endpoints need Ultra90 models. | F13: M4250 + M4350 datasheets
A14: R10 | B14: M4250-16XF | C14: Ports | D14: 1G SFP / AGM734 supported on ports 1-12 only. | E14: 1G endpoints/uplinks limited to 12 per switch. | F14: M4250 datasheet DS-M4250-9Nov23 (fw 13.0.4)
A15: R11 | B15: M4350 multi-gig models | C15: Ports | D15: 100M support limited: see Port_Notes (e.g. 24X4V ports 1-16 only, 40X4C none, 10G ports on M4X4V none). | E15: Legacy 100M AV/control devices must land on supported ports. | F15: M4350 datasheet DS-M4350-30May25 (fw 14.0) [file: M3450_Datasheet_30May25.pdf]
... A21: R17 | B21: All switches | C21: Environment | D21: Operating max: 45C PoE models, 50C non-PoE (M4250 12M2XF/16XF, M4350 non-PoE). | E21: Check rack ambient for closet/IDF installs. | F21: M4250 + M4350 datasheets

Sheet Model_Lookup
A1: Quick Model Lookup (example of how the tool reads the catalog)
A2: Pick a Product_ID in the yellow cell. All values below are formulas against the tables.
A4: Product_ID | B4: XSM4340CV
A5: Attribute | B5: Value
A6: Model_Name | B6: =IFERROR(INDEX(Products!$B$5:$B$500,MATCH($B$4,Products!$A$5:$A$500,0)),"")
A7: Family | B7: =IFERROR(INDEX(Products!$C$5:$C$500,MATCH($B$4,Products!$A$5:$A$500,0)),"")
A8: Category | B8: =IFERROR(INDEX(Products!$E$5:$E$500,MATCH($B$4,Products!$A$5:$A$500,0)),"")
A9: Form_Factor | B9: =IFERROR(INDEX(Products!$L$5:$L$500,MATCH($B$4,Products!$A$5:$A$500,0)),"")
A10: Width_Class | B10: =IFERROR(INDEX(Products!$N$5:$N$500,MATCH($B$4,Products!$A$5:$A$500,0)),"")
A11: Total_Ports | B11: =IFERROR(INDEX(Products!$AF$5:$AF$500,MATCH($B$4,Products!$A$5:$A$500,0)),"")
A12: PoE_Standard | B12: =IFERROR(INDEX(Products!$AJ$5:$AJ$500,MATCH($B$4,Products!$A$5:$A$500,0)),"")
A13: PoE_Ports | B13: =IFERROR(INDEX(Products!$AI$5:$AI$500,MATCH($B$4,Products!$A$5:$A$500,0)),"")
A14: PoE_Budget_Base_W | B14: =IFERROR(INDEX(Products!$AL$5:$AL$500,MATCH($B$4,Products!$A$5:$A$500,0)),"")
A15: PoE_Budget_Max_W | B15: =IFERROR(INDEX(Products!$AM$5:$AM$500,MATCH($B$4,Products!$A$5:$A$500,0)),"")
A16: PoE_Budget_Redundant_Max_W | B16: =IFERROR(INDEX(Products!$AN$5:$AN$500,MATCH($B$4,Products!$A$5:$A$500,0)),"")
A17: PSU_Compat_Group | B17: =IFERROR(INDEX(Products!$AW$5:$AW$500,MATCH($B$4,Products!$A$5:$A$500,0)),"")
A18: Power_Max_FullPoE_W | B18: =IFERROR(INDEX(Products!$AZ$5:$AZ$500,MATCH($B$4,Products!$A$5:$A$500,0)),"")
A19: Heat_Max_BTU_hr | B19: =IFERROR(INDEX(Products!$BA$5:$BA$500,MATCH($B$4,Products!$A$5:$A$500,0)),"")
A20: Switching_Fabric_Gbps | B20: =IFERROR(INDEX(Products!$BB$5:$BB$500,MATCH($B$4,Products!$A$5:$A$500,0)),"")
A21: Stacking | B21: =IFERROR(INDEX(Products!$BL$5:$BL$500,MATCH($B$4,Products!$A$5:$A$500,0)),"")
A22: SMPTE_ST2110 | B22: =IFERROR(INDEX(Products!$BP$5:$BP$500,MATCH($B$4,Products!$A$5:$A$500,0)),"")
A23: PTP | B23: =IFERROR(INDEX(Products!$BO$5:$BO$500,MATCH($B$4,Products!$A$5:$A$500,0)),"")
A24: Port_Speed_Constraints | B24: =IFERROR(INDEX(Products!$AH$5:$AH$500,MATCH($B$4,Products!$A$5:$A$500,0)),"")
A25: Support_Category | B25: =IFERROR(INDEX(Products!$BZ$5:$BZ$500,MATCH($B$4,Products!$A$5:$A$500,0)),"")
A27: Derived from other tables
A28: Orderable SKUs (count) | B28: =COUNTIF(SKUs!$A$5:$A$1000,$B$4)
A29: Best EPS PoE budget in matrix (W) | B29: =IFERROR(_xlfn.MAXIFS(PSU_PoE_Matrix!$G$5:$G$1000,PSU_PoE_Matrix!$A$5:$A$1000,$B$4),"")
A30: Best protected (N-1) PoE budget in matrix (W) | B30: =IFERROR(_xlfn.MAXIFS(PSU_PoE_Matrix!$J$5:$J$1000,PSU_PoE_Matrix!$A$5:$A$1000,$B$4),"")
A31: Compatibility rows (product-specific) | B31: =COUNTIFS(Compatibility!$A$5:$A$1000,"Product",Compatibility!$B$5:$B$1000,$B$4)
A32: How many WBE758 (39W) at max budget | B32: =IFERROR(MIN(INT(INDEX(Products!$AM$5:$AM$500,MATCH($B$4,Products!$A$5:$A$500,0))/INDEX(Products!$AP$5:$AP$500,MATCH("WBE758",Products!$A$5:$A$500,0))),INDEX(Products!$AI$5:$AI$500,MATCH($B$4,Products!$A$5:$A$500,0))),"")

Sheet Endpoints
A1: Endpoint Library (read by the BoM tool)
A2: Link speed drives line-rate design; PoE_W is the design allocation per device. Set NETGEAR_Product_ID to add the device itself to the BoM.
A4: Endpoint_ID | B4: Name | C4: Category | D4: Link_Speed_Gbps | E4: Media | F4: PoE_W | G4: Stream_Mbps | H4: NETGEAR_Product_ID | I4: Notes | J4: Timing
A5: EP-1G-TX | B5: 1G AV-over-IP encoder (TX) | C5: Video | D5: 1 | E5: Copper | F5: 13 | G5: 900 | I5: e.g. 1G HDMI/USB encoder; set PoE to maker spec
A6: EP-1G-RX | B6: 1G AV-over-IP decoder (RX) | C6: Video | D6: 1 | E6: Copper | F6: 13 | G6: 900
A7: EP-10G-TX | B7: 10G AV-over-IP encoder (copper) | C7: Video | D7: 10 | E7: Copper | F7: 0 | G7: 9500 | I7: SDVoE / uncompressed class; usually locally powered
A8: EP-10G-RX | B8: 10G AV-over-IP decoder (copper) | C8: Video | D8: 10 | E8: Copper | F8: 0 | G8: 9500
A9: EP-10G-FX | B9: 10G video endpoint (SFP+ fiber) | C9: Video | D9: 10 | E9: Fiber | F9: 0 | G9: 9500 | I9: Switch-side optic added to BoM
A10: EP-25G-2110 | B10: 25G ST 2110 device (SFP28) | C10: Video | D10: 25 | E10: Fiber | F10: 0 | G10: 20000 | I10: 25G SR optic added to BoM. ST 2110 timing (SMPTE 2059-2) needs a PTP boundary clock | J10: PTP-BC
A11: EP-DANTE | B11: Dante / AES67 audio device | C11: Audio | D11: 1 | E11: Copper | F11: 13 | G11: 20
A12: EP-PTZ | B12: PTZ camera (PoE++) | C12: Camera | D12: 1 | E12: Copper | F12: 60 | G12: 30
A13: EP-PANEL | B13: Touch panel | C13: Control | D13: 1 | E13: Copper | F13: 25 | G13: 5
A14: EP-CTRL | B14: Control processor | C14: Control | D14: 1 | E14: Copper | F14: 0 | G14: 5
A15: EP-PC | B15: PC / workstation | C15: IT | D15: 1 | E15: Copper | F15: 0 | G15: 1000
A16: EP-WBE758 | B16: NETGEAR WBE758 WiFi 7 AP | C16: Wireless | D16: 10 | E16: Copper | F16: 39 | G16: 5000 | H16: WBE758 | I16: From WBE758 datasheet (39W, 10G uplink)
A17: EP-WBE718 | B17: NETGEAR WBE718 WiFi 7 AP | C17: Wireless | D17: 2.5 | E17: Copper | F17: 25 | G17: 2500 | H17: WBE718 | I17: From WBE718 datasheet (25W, 2.5G uplink)
A18: EP-MILAN | B18: AVB / Milan audio device | C18: Audio | D18: 1 | E18: Copper | F18: 13 | G18: 10 | I18: Needs AVB-capable switches; M4250 AVB does not run over a LAG | J18: AVB

Sheet Port_Types
A1: Port Types (tells the BoM tool what every Ports_* column means)
A2: To add a new speed: add a Ports_<name> column in Products AND a row here. The tool needs no code change.
A4: Column_Name | B4: Port_Type | C4: Media | D4: Cage | E4: Max_Speed_Gbps | F4: Supported_Speeds_Gbps | G4: Endpoint_Capable | H4: Uplink_Capable | I4: PoE_Capable | J4: Breakout | K4: Notes
A5: Ports_1G_RJ45 | B5: 1G copper | C5: Copper | D5: RJ45 | E5: 1 | F5: 0.1,1 | G5: Yes | H5: No | I5: Yes | K5: 10/100/1000BASE-T
A6: Ports_2.5G_RJ45 | B6: 2.5G copper | C6: Copper | D6: RJ45 | E6: 2.5 | F6: 0.1,1,2.5 | G6: Yes | H6: No | I6: Yes | K6: 100M/1G/2.5GBASE-T
A7: Ports_5G_RJ45 | B7: 5G copper | C7: Copper | D7: RJ45 | E7: 5 | F7: 1,2.5,5 | G7: Yes | H7: No | I7: Yes | K7: Future-ready
A8: Ports_10G_RJ45 | B8: 10G copper (multi-gig) | C8: Copper | D8: RJ45 | E8: 10 | F8: 1,2.5,5,10 | G8: Yes | H8: No | I8: Yes | K8: 100M support varies per model - see Port_Speed_Constraints
A9: Ports_SFP_1G | B9: 1G SFP | C9: Fiber | D9: SFP | E9: 1 | F9: 1 | G9: Yes | H9: Yes | I9: No
A10: Ports_SFP_2.5G | B10: 1G/2.5G SFP | C10: Fiber | D10: SFP | E10: 2.5 | F10: 1,2.5 | G10: Yes | H10: Yes | I10: No
A11: Ports_SFP+_10G | B11: 10G SFP+ | C11: Fiber | D11: SFP+ | E11: 10 | F11: 1,10 | G11: Yes | H11: Yes | I11: No
A12: Ports_Combo_10G | B12: 10G combo (RJ45/SFP+) | C12: Fiber | D12: SFP+ | E12: 10 | F12: 1,10 | G12: Yes | H12: Yes | I12: No | K12: Counted once; engine treats as SFP+
A13: Ports_SFP28_25G | B13: 25G SFP28 | C13: Fiber | D13: SFP28 | E13: 25 | F13: 10,25 | G13: Yes | H13: Yes | I13: No | K13: M4350: one speed per 4-port block
A14: Ports_SFP56_50G | B14: 50G SFP56 | C14: Fiber | D14: SFP56 | E14: 50 | F14: 10,25,50 | G14: Yes | H14: Yes | I14: No | K14: Future-ready
A15: Ports_QSFP28_100G | B15: 100G QSFP28 | C15: Fiber | D15: QSFP28 | E15: 100 | F15: 40,100 | G15: No | H15: Yes | I15: No | J15: 4x25G | K15: Breakout not used by engine yet
A16: Ports_QSFP56_200G | B16: 200G QSFP56 | C16: Fiber | D16: QSFP56 | E16: 200 | F16: 40,100,200 | G16: No | H16: Yes | I16: No | J16: 4x50G | K16: Future-ready
A17: Ports_QSFPDD_400G | B17: 400G QSFP-DD | C17: Fiber | D17: QSFP-DD | E17: 400 | F17: 100,200,400 | G17: No | H17: Yes | I17: No | J17: 4x100G | K17: Future-ready

Sheet Tool_Settings
A1: Tool Settings (read by the BoM tool)
A2: Change behaviour and wording without code changes.
A4: Key | B4: Value | C4: Notes
A5: Catalog_Version | B5: 2026.10.01 | C5: Bump on every published update
A6: Validation_Contact_Email | B6: proavdesign@netgear.com | C6: Shown to users; from M4250 datasheet
A7: Disclaimer | B7: This bill of materials is generated automatically as a budgetary estimate. It must be validated by the ProAV Design team before ordering. | C7: Shown on screen and in every export
A8: Gateway_Product_ID | B8: PR460X | C8: Router added when 'include gateway' is on
A9: Support_SKU_Pattern | B9: PMB03{years}{cat}-10000S | C9: {years}=1/3/5, {cat}=digit from Support_Category
A10: PSU_Efficiency | B10: 0.9 | C10: Used for estimated draw = no-PoE max + PoE load / efficiency
A11: Default_Spare_Pct | B11: 10
A12: Default_PoE_Headroom_Pct | B12: 20
A13: Default_Oversubscription | B13: 1 | C13: 1 = line-rate
A14: Max_LAG_Members | B14: 8 | C14: Max uplinks per switch
A15: Min_Uplink_Gbps | B15: 10 | C15: Slowest uplink speed to the core. 10 keeps headroom even when only audio or control devices are in a room; 1 allows 1G uplinks
A16: Uplink_LAG_Sizes | B16: 1,2,4,8 | C16: Allowed uplink counts per LAG. Powers of 2 hash evenly; 1 only when single uplink is allowed
A17: In_Rack_Max_m | B17: 20 | C17: MDF links at or below this use DAC/AOC
A18: Endpoint_Speeds_Gbps | B18: 1,2.5,5,10,25,50,100 | C18: Speeds offered in the endpoint library

Sheet Data_Dictionary
A1: Data Dictionary
A2: Every column, its unit and meaning. Bottom block = fields recommended for the next iteration.
A4: Sheet | B4: Column | C4: Group | D4: Unit | E4: Type | F4: Description
A5: Products | B5: Product_ID | C5: Identity | E5: Text (key) | F5: Base model number (unique key used by every other sheet). e.g. GSM4212PX
A6: Products | B6: Model_Name | C6: Identity | E6: Text | F6: Marketing model name
A7: Products | B7: Family | C7: Identity | E7: List | F7: Product family/series (M4250, M4350, PR460X, WBE7xx...)
A8: Products | B8: Product_Line | C8: Identity | E8: Text | F8: Brand line (AV Line, AV and IT, Insight Pro)
A9: Products | B9: Category | C9: Identity | E9: List | F9: Switch / Router / Access Point
A10: Products | B10: Role | C10: Identity | E10: List | F10: Design role the tool can filter on (Access/Edge, Aggregation/Core, Gateway, Wireless AP)
A11: Products | B11: Management | C11: Identity | E11: Text | F11: Management planes supported
A12: Products | B12: Lifecycle_Status | C12: Commercial | E12: List | F12: Active / NPI / EOS / EOL - tool should only offer Active by default
A13: Products | B13: List_Price_USD | C13: Commercial | D13: USD | E13: Number | F13: TO FILL from price book
A14: Products | B14: Lead_Time_Wks | C14: Commercial | D14: weeks | E14: Number | F14: TO FILL from ops/distribution
A15: Products | B15: EOS_Date | C15: Commercial | D15: date | E15: Date | F15: TO FILL (end of sale)
A16: Products | B16: Form_Factor | C16: Physical | E16: List | F16: Desktop / 1U rack / 2U rack / Wall-ceiling
A17: Products | B17: Rack_Units | C17: Physical | D17: U | E17: Number | F17: Rack units (blank for non-rack)
A18: Products | B18: Width_Class | C18: Physical | E18: List | F18: Full width / Half width / Desktop / Ceiling-Wall (half-width = 2 per RU)
A19: Products | B19: Width_mm | C19: Physical | D19: mm | E19: Number | F19: Width
A20: Products | B20: Depth_mm | C20: Physical | D20: mm | E20: Number | F20: Depth (rack depth check)
A21: Products | B21: Height_mm | C21: Physical | D21: mm | E21: Number | F21: Height
A22: Products | B22: Weight_kg | C22: Physical | D22: kg | E22: Number | F22: Unit weight
A23: Products | B23: Ports_1G_RJ45 | C23: Ports | D23: count | E23: Number | F23: 10/100/1000BASE-T RJ45 ports (PoE and non-PoE)
A24: Products | B24: Ports_2.5G_RJ45 | C24: Ports | D24: count | E24: Number | F24: Up-to-2.5GBASE-T RJ45 ports
A25: Products | B25: Ports_10G_RJ45 | C25: Ports | D25: count | E25: Number | F25: Multi-gig up-to-10GBASE-T RJ45 ports
A26: Products | B26: Ports_SFP_1G | C26: Ports | D26: count | E26: Number | F26: 1G SFP cages
A27: Products | B27: Ports_SFP_2.5G | C27: Ports | D27: count | E27: Number | F27: 1G/2.5G SFP cages
A28: Products | B28: Ports_SFP+_10G | C28: Ports | D28: count | E28: Number | F28: 1G/10G SFP+ cages
A29: Products | B29: Ports_SFP28_25G | C29: Ports | D29: count | E29: Number | F29: 10G/25G SFP28 cages
A30: Products | B30: Ports_QSFP28_100G | C30: Ports | D30: count | E30: Number | F30: 40G/100G QSFP28 (4x25G breakout on M4350)
... A37: Products | B37: Max_1G_SFP_Modules | C37: Ports | D37: count | E37: Number | F37: Machine-readable cap on 1G SFP modules (blank = no cap)
A38: Products | B38: Port_Speed_Constraints | C38: Ports | E38: Text | F38: Speed/port-range caveats the tool must respect
A39: Products | B39: PoE_Ports | C39: PoE (PSE) | D39: count | E39: Number | F39: Number of PoE-capable ports
A40: Products | B40: PoE_Standard | C40: PoE (PSE) | E40: List | F40: None / 802.3at PoE+ / 802.3bt Ultra90 PoE++ / PD (device consumes PoE)
A41: Products | B41: PoE_Max_W_per_Port | C41: PoE (PSE) | D41: W | E41: Number | F41: Max class per port (30 or 90W)
A42: Products | B42: PoE_Budget_Base_W | C42: PoE (PSE) | D42: W | E42: Number | F42: Budget as shipped (no extra PSU)
A43: Products | B43: PoE_Budget_Max_W | C43: PoE (PSE) | D43: W | E43: Number | F43: Max budget with best PSU config (see PSU_PoE_Matrix)
A44: Products | B44: PoE_Budget_Redundant_Max_W | C44: PoE (PSE) | D44: W | E44: Number | F44: Max protected budget when one PSU fails
A45: Products | B45: PoE_Avg_W_per_Port_at_Max | C45: PoE (PSE) | D45: W | E45: Formula | F45: CALCULATED: max budget / PoE ports (quick 'can every port run X W' check)
A46: Products | B46: PD_Max_Draw_W | C46: PoE (PD) | D46: W | E46: Number | F46: For powered devices (APs etc.): max draw to subtract from switch budget
A47: Products | B47: PD_Required_PoE | C47: PoE (PD) | E47: Text | F47: PoE standard needed for full function
A48: Products | B48: PD_Uplink_Speed | C48: PoE (PD) | E48: Text | F48: Uplink port speed the device needs
A49: Products | B49: PSU_Type | C49: Power | E49: Text | F49: Internal fixed / external adapter / modular
A50: Products | B50: PSU_Internal_W | C50: Power | D50: W | E50: Number | F50: Internal/included PSU rating
A51: Products | B51: PSU_Fixed_Qty | C51: Power | D51: count | E51: Number | F51: Fixed/included PSUs
A52: Products | B52: PSU_Modular_Slots | C52: Power | D52: count | E52: Number | F52: Empty modular PSU slots / extra DC inputs
A53: Products | B53: PSU_Compat_Group | C53: Power | E53: Text | F53: Which modular PSU family fits (details in Compatibility)
A54: Products | B54: Power_Idle_W | C54: Power | D54: W | E54: Number | F54: Idle/standby consumption
A55: Products | B55: Power_Max_NoPoE_W | C55: Power | D55: W | E55: Number | F55: All ports, line rate, no PoE
A56: Products | B56: Power_Max_FullPoE_W | C56: Power | D56: W | E56: Number | F56: All ports, max PoE budget (max PSU config)
A57: Products | B57: Heat_Max_BTU_hr | C57: Power | D57: BTU/hr | E57: Formula | F57: CALCULATED: max power x 3.412 (UPS/HVAC sizing)
A58: Products | B58: Switching_Fabric_Gbps | C58: Performance | D58: Gbps | E58: Number | F58: Non-blocking fabric
A59: Products | B59: Throughput_Mpps | C59: Performance | D59: Mpps | E59: Number | F59: 64-byte forwarding rate
A60: Products | B60: Packet_Buffer_Mb | C60: Performance | D60: Mb | E60: Number | F60: Packet buffer (important for AV bursts)
A61: Products | B61: RAM_GB | C61: Performance | D61: GB | E61: Number | F61: System memory
A62: Products | B62: CPU | C62: Performance | E62: Text | F62: CPU
A63: Products | B63: MAC_Table | C63: Performance | D63: entries | E63: Number | F63: MAC address table
A64: Products | B64: Max_VLANs | C64: Performance | D64: count | E64: Number | F64: Max concurrent VLANs
A65: Products | B65: IGMP_Groups | C65: Performance | E65: Text | F65: Multicast group capacity (AV multicast sizing)
A66: Products | B66: Max_LAGs | C66: Performance | E66: Text | F66: LAG groups x members
A67: Products | B67: L3_Feature_Set | C67: Features | E67: Text | F67: Routing capability
A68: Products | B68: Stacking | C68: Features | E68: List | F68: Yes/No
A69: Products | B69: Stack_Max_Units | C69: Features | D69: count | E69: Number | F69: Max stack members
A70: Products | B70: AVB | C70: Features | E70: Text | F70: AVB/Milan support and limits
A71: Products | B71: PTP | C71: Features | E71: Text | F71: PTP role (TC/BC/GM) and profiles
A72: Products | B72: SMPTE_ST2110 | C72: Features | E72: List | F72: Yes/No
A73: Products | B73: IGMP_Plus | C73: Features | E73: List | F73: Yes/No
A74: Products | B74: Engage_Support | C74: Features | E74: Text | F74: Managed by NETGEAR Engage
A75: Products | B75: Insight_Support | C75: Features | E75: Text | F75: Managed by NETGEAR Insight
A76: Products | B76: OpTemp_Max_C | C76: Environment | D76: C | E76: Number | F76: Max operating ambient
A77: Products | B77: Airflow | C77: Environment | E77: Text | F77: Airflow direction / fanless
A78: Products | B78: Fan_Off_Mode | C78: Environment | E78: Text | F78: Fanless operation capability and limits
A79: Products | B79: Acoustic_Quiet_25C_dBA | C79: Environment | D79: dBA | E79: Number | F79: Lowest Quiet-mode SPL at 25C (from acoustic table)
A80: Products | B80: MTBF_25C_hours | C80: Environment | D80: hours | E80: Number | F80: MTBF at 25C
A81: Products | B81: Warranty | C81: Commercial | E81: Text | F81: Hardware warranty
A82: Products | B82: Support_Category | C82: Commercial | E82: Text | F82: OnCall category / support pack family
A83: Products | B83: TAA_SKU | C83: Commercial | E83: Text | F83: TAA-compliant orderable variant
A84: Products | B84: Included_Subscription | C84: Commercial | E84: Text | F84: Bundled cloud subscription
A85: Products | B85: WAN_Ports | C85: Router | E85: Text | F85: Router: WAN ports / modes
A86: Products | B86: WAN_Throughput | C86: Router | E86: Text | F86: Router: LAN-WAN throughput
A87: Products | B87: VPN_Capacity | C87: Router | E87: Text | F87: Router: VPN tunnels / throughput
A88: Products | B88: Max_Clients | C88: Router | D88: count | E88: Number | F88: Router: concurrent clients
A89: Products | B89: WiFi_Standard | C89: Wireless | E89: Text | F89: AP: WiFi generation/bands
A90: Products | B90: WiFi_Streams | C90: Wireless | E90: Text | F90: AP: spatial streams
A91: Products | B91: WiFi_Max_Gbps | C91: Wireless | D91: Gbps | E91: Number | F91: AP: aggregate theoretical PHY rate
A92: Products | B92: SSIDs | C92: Wireless | D92: count | E92: Number | F92: AP: max SSIDs
A93: Products | B93: Source_Datasheet | C93: Governance | E93: Text | F93: Datasheet doc ID / version the row came from
A94: Products | B94: Last_Verified | C94: Governance | D94: date | E94: Date | F94: Date row was last checked against a datasheet
A95: Products | B95: Data_Notes | C95: Governance | E95: Text | F95: Conflicts, assumptions, caveats
A96: SKUs | B96: Orderable_SKU | E96: Text (key) | F96: Exact orderable part number incl. region suffix
A97: Accessories | B97: Base_Model | E97: Text | F97: Groups SKU variants; referenced by Compatibility.Accessory_Base
A98: Accessories | B98: Output_W_110VAC / 220VAC | D98: W | E98: Number | F98: PSU output by input voltage (drives PoE sizing)
A99: Compatibility | B99: Scope_Type / Scope_Value | E99: List / Text | F99: 'Product' + Product_ID, or 'Family' + Family name
A100: Compatibility | B100: Max_Qty | D100: count | E100: Number | F100: Max units per product (PSU slots etc.)
A101: PSU_PoE_Matrix | B101: PoE_Budget_EPS_W | D101: W | E101: Number | F101: Total PoE budget with all PSUs in config powered
A102: PSU_PoE_Matrix | B102: PoE_If_Internal_PSU_Fails_W | D102: W | E102: Number | F102: Datasheet value with internal PSU disconnected
A103: PSU_PoE_Matrix | B103: PoE_If_One_Module_Fails_W | D103: W | E103: Number | F103: Budget of same config with one module fewer
A104: PSU_PoE_Matrix | B104: PoE_Budget_Protected_W | D104: W | E104: Formula | F104: MIN of the two failure cases = guaranteed budget with redundancy
A105: Recommended addition | B105: Per-port PoE class map | C105: Ports | E105: Table | F105: Which port ranges are PoE / Ultra90 when a model mixes types (e.g. M4350-44M4X4V)
A106: Recommended addition | B106: Uplink vs access port designation | C106: Ports | E106: Table | F106: Lets the engine auto-assign uplinks per IDF/MDF
A107: Recommended addition | B107: Stacking cables / modules | C107: Accessories | E107: Rows | F107: Needed to BOM M4350 stacks
...

Sheet Data_Gaps
A1: Open Data Gaps & Datasheet Conflicts
A2: Resolve these before trusting the affected rows in customer BoMs.
A4: Area | B4: Issue | C4: Action / Assumption Used
A5: M4350 | B5: Filename says 'M3450' but content is the M4350 datasheet (DS-M4350-30May25). | C5: Rename file to avoid confusion in source tracking.
A6: M4350 | B6: No NETGEAR-branded 25G/100G optics; optic.ca modules from KB 000066694 loaded instead. 25G DAC 2/3/5m listed in KB but only 1m seen on optic.ca shop. Breakout cables loaded but not used by engine. | C6: Confirm 25G DAC lengths with optic.ca; add M4500 when it joins the catalog (KB also covers M4500).
A7: M4350 | B7: Stacking cables/modules and max LAG count not extracted. | C7: Confirm from full spec pages; add to Accessories/Products.
A8: M4350 | B8: APS1200Wv2 110VAC rating not stated (only 1,200W @110/220V), yet PoE matrix shows lower budgets at 110VAC. | C8: Confirm actual 110V output with PLM.
A9: M4350 | B9: Datasheet typo: 24M4X4V 2x APS1200Wv2 @220VAC shows '2.292W'. | C9: Loaded as 2,292W - confirm.
A10: M4250 | B10: M4250-16XF weight 1.74 kg (product page) vs 2.80 kg (spec table). | C10: Loaded 2.80 kg - confirm.
A11: M4250 | B11: M4250-9G1F-PoE+ throughput 14.88 vs 14.80 Mpps. | C11: Loaded 14.88 - minor.
A12: M4350 | B12: 44M4X4V datasheet states max redundant budget 1,794W; matrix-derived N-1 (2x APS2000W @220V, one module failed) is 1,786W. | C12: Products keeps 1,794W (datasheet); matrix shows derived values - confirm with PLM.
A13: PR460X | B13: Concurrent connections 60,000 (spec) vs 250,000 (features). | C13: Confirm; affects sizing only for large residential/commercial.
A14: PR460X | B14: Security license SKUs marked WIP; Sprint/Overdrive support SKUs not listed. | C14: Get current SKUs from PLM.
A15: WBE718 | B15: Weight 0.69 kg labelled 2.09 lb (should be ~1.52 lb). Only NA/EU SKUs listed. | C15: Confirm weight and APAC SKU.
... A18: All | B18: Engage 'select access points' list not defined in datasheets. | C18: Confirm which WBE models Engage v2 supports.

Sheet Lists
A1: Validation Lists
A2: Edit these lists to change dropdowns in Products / Accessories / Compatibility.
A4: Category | B4: Role | C4: Status | D4: Form_Factor | E4: Width_Class | F4: PoE_Standard | G4: Yes_No | H4: Acc_Category | I4: Scope_Type | J4: Link_Speed_Gbps | K4: Media
A5: Switch | B5: Access / Edge | C5: Active | D5: Desktop | E5: Full width | F5: None | G5: Yes | H5: Optic | I5: Product | J5: 1 | K5: Copper
A6: Router | B6: Aggregation | C6: NPI | D6: 1U rack | E6: Half width | F6: 802.3af PoE | G6: No | H6: DAC | I6: Family | J6: 2.5 | K6: Fiber
A7: Access Point | B7: Aggregation / Core | C7: EOS | D7: 2U rack | E7: Desktop | F7: 802.3at PoE+ | H7: AOC | J7: 5
A8: Controller | B8: Gateway / Router | C8: EOL | D8: 1U rack (reversible ears) | E8: Ceiling/Wall | F8: 802.3bt Ultra90 PoE++ | H8: PSU Module | J8: 10
A9: Other | B9: Wireless AP (indoor) | D9: Wall / ceiling | F9: PD | H9: Power Adapter | J9: 25
B10: Wireless AP (outdoor) | D10: Outdoor | H10: PSU Tray | J10: 50
H11: License | J11: 100
H12: Support | J12: 200
H13: Service | J13: 400
H14: Stacking
H15: Mounting
H16: Breakout Cable
